Workbook
Name FX_KRW: '13_FXAssumptions'!$C$6
Name BASE_WAGE: '13_FXAssumptions'!$C$7
Name WAGE_MULT: '13_FXAssumptions'!$C$8
Name ER_RATE: '13_FXAssumptions'!$C$9
Name LOCAL_HC: '13_FXAssumptions'!$C$10
Name OFFICE_SQM: '13_FXAssumptions'!$C$11
Name OFFICE_RENT: '13_FXAssumptions'!$C$12
Name DEP_MONTHS: '13_FXAssumptions'!$C$13
Name INV_DAYS: '13_FXAssumptions'!$C$14
Name MONTHLY_SALES: '13_FXAssumptions'!$C$15
Name CAP_MULT: '13_FXAssumptions'!$C$16
Name T0: '16_Timeline'!$C$4

Sheet 01_README
A1: SKTC 중국법인 설립 검토 — Raw File Data
A2: 원자료 → 법적·사업적 판단 → 계산·비교 → PPT 결론을 ID로 추적하는 워크북
A3: 조사 기준일 2026-10-06 · 단위·상태는 각 열 머리글 참조
A5: 목적 | B5: TC 중국법인의 운영 구조·입지(강소성 우선)·인허가·비용·일정 의사결정 근거 보관 및 갱신
A6: 조사 기준일 | B6: 2026-10-06 (내부 회의일). 작업일도 동일
A7: 수정일 / 버전 | B7: 2026-10-06 / v1.0
A8: 조사 한계 | B8: 이 작업 환경의 네트워크 정책으로 중국 정부 사이트 원문을 직접 열지 못함. 웹 검색 결과 요약으로 내용을 확인했으며, 공식 출처라도 상태를 '공식 출처·요약 확인'으로 표시(원문 조문 대조 필요)
A9: ID 체계 | B9: SRC(출처) → EVD(근거) → 판단 시트(06·07·08·10) / CITY(도시)·SITE(시설)·MAT(제품)·ASM(가정)·CST(비용)·T(일정)·R(리스크)
A10: 입력 셀 | B10: 파란 글자·연파랑 칸 = 바꿀 수 있는 입력값 (13_FXAssumptions, 08 점수, 16 기간)
A11: 수식 셀 | B11: 검정 글자 = 수식. 계산 결과를 붙여넣은 칸 없음
A12: 미확인 값 | B12: 빈칸 = 견적 필요·정보 없음. 0으로 처리하지 않으며, 합계 옆에 '미완성(견적 n건)'으로 표시
A13: 외부 연결 | B13: 외부 링크·매크로 없음. 출처 URL은 하이퍼링크(클릭 시 브라우저)
A14: 사용 방법 | B14: ① 13 시트 입력값·14 시트 단가를 견적으로 교체 → 15 합계 자동 갱신 ② 08 점수·가중치 변경 → 순위 갱신 ③ 16 기간 변경 → 일정 갱신
A16: 정보 상태 범례
A17: 공식 출처·요약 확인 | B17: 정부·기관 공식 URL을 찾았고 내용은 검색 결과 요약으로 확인. 원문 조문 대조 전 (네트워크 정책상 원문 미열람)
A18: 전문가 자료 | B18: 법무법인·인증 컨설팅·회계법인 등 전문가 해설. 원문과 대조 필요
A19: 언론·기타 | B19: 언론 보도·업체 자료. 사실 확인용 보조 근거
A20: 내부 제공 | B20: 2026-10-06 내부 회의에서 나온 내용. 검증 전
A21: 분석 가정 | B21: 의사결정 비교를 위한 분석상 가정. 견적·실측으로 교체 필요
A22: 기관 확인 필요 | B22: 담당 기관·업체에 질의해야 확정되는 항목 (문의 예정)
A23: 정보 없음 | B23: 현재 정보 없음 (0이 아님)
A25: 시트 구성
A26: 02_ExecutiveSummary | B26: PPT 핵심 결론·근거 ID
A27: 03_SourceRegister | B27: 출처 40건
A28: 04_EvidenceRaw | B28: 근거 36건 (원문 핵심 구절·한국어 해석)
A29: 05_Materials | B29: 제품 입력자료·규제 시나리오 A~D
A30: 06_LegalMatrix | B30: 법적 쟁점별 결론
A31: 07_PermitPaths | B31: 허가 절차·기간
A32: 08_CityComparison | B32: 도시 관문·점수·민감도 (수식)
A33: 09_SitesWarehouses | B33: 단지·창고 후보
A34: 10_OperatingModels | B34: 운영 구조 A~G
A35: 11_MPComparison | B35: MP 활용 vs TC 법인
A36: 12_LogisticsStaff | B36: 직선거리(수식)·인력
A37: 13_FXAssumptions | B37: 환율·단가 입력
... A43: 19_Glossary_Q | B43: 용어 해설·기관 질문지

Sheet 02_ExecutiveSummary
A1: 02_ExecutiveSummary | 핵심 결론 (PPT 02·28장)
A2: 숫자 칸은 다른 시트 수식 참조. 결론은 조건부이며 '확정 불가' 항목은 그대로 표시
A4: 구분 | B4: 내용 | C4: 조건·전제 | D4: 근거 충족 상태 | E4: PPT 페이지 | F4: 근거 ID
A5: 권고 운영 구조 | B5: B안: TC 독자 법인 + 무저장 위험화학품 경영허가 + 허가 외부 창고(3PL) | C5: 제품이 위험화학품·신규물질(시나리오 A)일 때 기준 | D5: 중 (규정 근거 기반, 기관 확인 전) | E5: 02, 08, 22 | F5: EVD-014, EVD-015
A6: 강소성 1순위 | B6: 무석 신오구 (법인·영업) + 무석 관할 인정 화공원구 창고 | C6: 창고 운영사의 품목·물성 수용 | D6: 중 | E6: 15, 18 | F6: EVD-014, EVD-020
A7: 강소성 차선 | B7: 쑤저우 SIP 법인 + 장자강 扬子江国际化学工业园 창고 | C7: 쑤저우 세칙·창고 품목 확인 | D7: 중 | E7: 16, 18 | F7: EVD-021
A8: 인근 대안 1·2 | B8: 상하이(수입항·보세 물류) / 허페이(CXMT 대응) | C8: 강소성 창고 미확보 시 | D8: 하 | E8: 20, 21 | F8: SRC-031, EVD-029
A9: 연말 기한 | B9: 备案 접수 중단(2026-08-15)·기존 备案은 2026-12-31까지 등록증 취득 | C9: TC 제품이 备案으로 수입돼 왔을 때 | D9: 중 (공식 통지, 원문 대조 필요) | E9: 05, 26 | F9: EVD-003
A10: 등록 주체 | B10: 현행: 해외 생산자+대리인 가능 / 개정 초안: 중국 생산·수입기업만 | C10: 개정 최종 공포 여부 | D10: 중 | E10: 05, 10 | F10: EVD-001, EVD-002
A11: 생산설비 필요 가설 | B11: 단순 수입·판매에는 생산허가·생산설비 불필요 (근거 기반) | C11: 충진·소분 등 가공 없음 | D11: 중 | E11: 05, 07 | F11: EVD-009, EVD-011
A12: B안 초기 일회성 비용 (확인 가능분, CNY) | B12: ='15_CostModel'!C6 -> 확인분 없음 | C12: ='15_CostModel'!E6 -> 미완성(견적 6건)
A13: B안 연간 고정비 (확인 가능분, CNY) | B13: ='15_CostModel'!C8 -> 715843.98 | C13: ='15_CostModel'!E8 -> 미완성(견적 5건)
A14: B안 연 인건비 최소 시나리오 (CNY) | B14: ='15_CostModel'!D14 -> 715843.98 | C14: 분석 가정
A15: 무석 종합점수 (기본 가중치) | B15: ='08_CityComparison'!Q13 -> 76 | C15: 분석 가정 점수
A16: 기준 시나리오 초도 공급 예상일 | B16: ='16_Timeline'!L19 -> 46587 | C16: 분석 가정 일정

Sheet 03_SourceRegister
A1: 03_SourceRegister | 출처 목록
A2: 확인일은 모두 조사 기준일. '공식여부'는 발행 기관 기준이며, 원문 열람 여부와 별개
A3: 조사 기준일 2026-10-06 · 단위·상태는 각 열 머리글 참조
A5: 출처 ID | B5: 문서명 | C5: 기관·발행자 | D5: 문서 종류 | E5: 공식 여부 | F5: 적용 지역 | G5: 발령일 | H5: 시행일 | I5: 유효 상태 | J5: 원문 URL | K5: 확인일 | L5: 관련 페이지·조문 | M5: 주의사항 | N5: 정보 상태
A6: SRC-001 | B6: 新化学物质环境管理登记办法 (生态环境部令第12号) | C6: 生态环境部 | D6: 부문규장 | E6: 공식 | F6: 전국 | G6: 2020-04-29 | H6: 2021-01-01 | I6: 현행 (2026 개정 추진 중) | J6: https://www.gov.cn/zhengce/zhengceku/2020-05/11/content_5510520.htm | K6: 2026-10-06 | L6: 신청인·해외 생산자 대리인·등록 유형 | M6: 개정 시 신청 주체 변경 가능 | N6: 공식 출처·요약 확인
A7: SRC-002 | B7: 新化学物质环境管理登记指南 | C7: 生态环境部 | D7: 지침 | E7: 공식 | F7: 전국 | G7: 2020-11-17 | H7: 2021-01-01 | I7: 현행 | J7: https://www.mee.gov.cn/xxgk2018/xxgk/xxgk01/202011/W020201119648157169625.pdf | K7: 2026-10-06 | L7: 대리인 요건·시험자료 요건 | N7: 공식 출처·요약 확인
A8: SRC-003 | B8: 关于公开征求《新化学物质环境管理登记办法（修订征求意见稿）》意见的函 | C8: 生态环境部 | D8: 의견수렴 공문 | E8: 공식 | F8: 전국 | G8: 2026-06-11 | H8: - | I8: 초안 (의견수렴 2026-07-12 마감) | J8: https://www.mee.gov.cn/xxgk2018/xxgk/xxgk06/202606/t20260611_1159143.html | K8: 2026-10-06 | L8: 개정 초안 공개 | M8: 초안 — 확정 규정 아님 | N8: 공식 출처·요약 확인
A9: SRC-004 | B9: 新化学物质环境管理登记办法（修订征求意见稿）附件2 | C9: 生态环境部 | D9: 개정 초안 | E9: 공식 | F9: 전국 | G9: 2026-06-11 | H9: - | I9: 초안 | J9: https://www.mee.gov.cn/xxgk2018/xxgk/xxgk06/202606/W020260611818449079632.pdf | K9: 2026-10-06 | L9: 신청 주체·등록 유형·경과조치 | M9: 최종 공포 여부 기관 확인 필요 | N9: 공식 출처·요약 확인
A10: SRC-005 | B10: 生态环境部办公厅关于新化学物质环境管理登记有关事项的通知 (环办固体函〔2026〕301号) | C10: 生态环境部 판공청 | D10: 통지 | E10: 공식 | F10: 전국 | G10: 2026-07-31 | H10: 2026-08-15 | I10: 현행 (검색 요약 기준) | J10: https://www.mee.gov.cn/xxgk2018/xxgk/xxgk06/202608/t20260804_1163416.html | K10: 2026-10-06 | L10: 备案 접수 중단(8/15)·기존 备案의 등록증 전환(12/31) | M10: 연말 기한 문구의 정확한 출처(통지/개정안) 원문 대조 필요 | N10: 공식 출처·요약 확인
A11: SRC-006 | B11: 생태환경법전(生态环境法典) 시행과 신규화학물질 등록 개정 해설 | C11: 瑞旭集团(CIRS) | D11: 전문가 해설 | E11: 비공식 | F11: 전국 | G11: 2026 | H11: - | I11: - | J11: https://www.cirs-group.com/cn/chemicals/sheng-tai-huan-jing-fa-dian-luo-di-zhi-ji-xin-hua-xue-wu-zhi-deng-ji-zhi-du-ying-lai-zhong-gou-shi-xiu-ding | K11: 2026-10-06 | L11: 신청 주체를 중국 내 생산·수입 기업으로 한정하는 개정 방향 | M11: 전문가 해석 | N11: 전문가 자료
A12: SRC-007 | B12: China's New Ecological and Environmental Code: Key Highlights | C12: Hogan Lovells | D12: 전문가 해설 | E12: 비공식 | F12: 전국 | G12: 2026 | H12: 2026-08-15 | I12: - | J12: https://www.hoganlovells.com/en/publications/chinas-new-ecological-and-environmental-code-key-highlights-and-practical-implications | K12: 2026-10-06 | L12: 생태환경법전 2026-03-12 채택·2026-08-15 시행 | N12: 전문가 자료
A13: SRC-008 | B13: 2026新化学物质登记办法修订解读 FAQ | C13: REACH24H | D13: 전문가 해설 | E13: 비공식 | F13: 전국 | G13: 2026 | H13: - | I13: - | J13: https://www.reach24h.com/chemical/industry-news/faq-revision-draft | K13: 2026-10-06 | L13: 기존 등록증 유효·변경 시 재신청 | N13: 전문가 자료
A14: SRC-009 | B14: 中华人民共和国危险化学品安全法 | C14: 全国人大常委会 | D14: 법률 | E14: 공식 | F14: 전국 | G14: 2025-12-27 | H14: 2026-05-01 | I14: 현행 | J14: http://www.npc.gov.cn/npc/c2/c30834/202512/t20251227_450708.html | K14: 2026-10-06 | L14: 제53조 경영허가제·제54조 경영 조건·제56조 저장·제122조 수출입 | M14: 조문 번호는 검색 요약 기준 — 원문 대조 필요 | N14: 공식 출처·요약 확인
A15: SRC-010 | B15: 危险化学品经营许可证管理办法 (原安监总局令第55号, 2015修正) | C15: 应急管理部(原安监总局) | D15: 부문규장 | E15: 공식 | F15: 전국 | G15: 2012-07-17 | H15: 2012-09-01 | I15: 현행 (신법 시행 후 개정 여부 확인 필요) | J15: https://www.mem.gov.cn/gk/gwgg/agwzlfl/zjl_01/201505/t20150527_233724.shtml | K15: 2026-10-06 | L15: 제6조 기본 조건·발급 기관·유효기간 3년 | M15: 위험화학품안전법 하위 규정 정비 여부 확인 | N15: 공식 출처·요약 확인
A16: SRC-011 | B16: 无锡市危险化学品经营许可工作实施细则（试行） | C16: 无锡市应急管理局·无锡市行政审批局 | D16: 지방 규범성 문건 | E16: 공식 | F16: 무석시 | G16: 2023-03-22 | H16: 2023 | I16: 시행 (试行) | J16: http://yjglj.wuxi.gov.cn/doc/2023/03/22/3913243.shtml | K16: 2026-10-06 | L16: 경영 방식: 무저장·유저장·임차저장·주유소 | M16: 세부 조건은 원문 대조 필요 | N16: 공식 출처·요약 확인
A17: SRC-012 | B17: 南京市危险化学品经营许可工作实施细则（试行） | C17: 南京市应急管理局 | D17: 지방 규범성 문건 | E17: 공식 | F17: 난징시 | G17: 2022-01-17 | H17: 2022 | I17: 시행 (试行) | J17: http://safety.nanjing.gov.cn/njsaqscjdglj/202201/t20220117_3263584.html | K17: 2026-10-06 | L17: 경영 방식·심사 권한 | N17: 공식 출처·요약 확인
A18: SRC-013 | B18: 省政府关于公布江苏省化工园区认定复核通过名单（第一批）的通知 | C18: 江苏省人民政府 | D18: 공고 | E18: 공식 | F18: 강소성 | G18: 2023-06-02 | H18: 2023-06-02 | I18: 현행 (2차 명단 별도) | J18: http://www.jiangsu.gov.cn/art/2023/6/2/art_46143_10911831.html | K18: 2026-10-06 | L18: 인정 화공원구 23곳 | M18: 2차 명단(苏政发〔2023〕115号) 원문 미확보 | N18: 공식 출처·요약 확인
A19: SRC-014 | B19: 江苏省化工园区管理办法 | C19: 江苏省人民政府 | D19: 지방정부 규범 | E19: 공식 | F19: 강소성 | G19: 2023-12-25 | H19: 2024 | I19: 현행 | J19: https://www.jiangsu.gov.cn/art/2023/12/25/art_46143_11108896.html | K19: 2026-10-06 | L19: 원구 내 생산·저장 구역 분리 | N19: 공식 출처·요약 확인
A20: SRC-015 | B20: 江苏省化工产业结构调整限制和淘汰目录（2025年本） | C20: 江苏省人民政府办公厅 | D20: 목록 | E20: 공식 | F20: 강소성 | G20: 2025 | H20: 2026-01-24 | I20: 현행 (2031-01-23까지) | J20: https://hgt.cirs-group.com/lawinfo/detail/f8n5oq59uayo | K20: 2026-10-06 | L20: 화공 프로젝트 제한·도태 | M20: 제조 활동(F안) 검토 시 확인 | N20: 공식 출처·요약 확인
A21: SRC-016 | B21: 危险化学品登记管理办法 (原安监总局令第53号) | C21: 应急管理部(原安监总局) | D21: 부문규장 | E21: 공식 | F21: 전국 | G21: 2012-07-01 | H21: 2012-08-01 | I21: 현행 (신법 하위 정비 확인) | J21: https://www.expcenter.chemeng.tsinghua.edu.cn/Standards/国内化学品安全管理相关法规标准/部门规章/部门规章/危险化学品登记管理办法-总局令53号.docx | K21: 2026-10-06 | L21: 생산·수입기업의 위험화학품 등록(최초 수입 전) | M21: 청화대 자료실 사본 | N21: 공식 출처·요약 확인
A22: SRC-017 | B22: 海关总署公告2020年第129号 (进出口危险化学品及其包装检验) | C22: 海关总署 | D22: 공고 | E22: 공식 | F22: 전국 | G22: 2020-12 | H22: 2021-01-10 | I22: 현행 | J22: https://www.cirs-group.com/cn/chemicals/shang-pin-jian-yan-jin-kou-wei-xian-hua-xue-pin-tong-guan-tips | K22: 2026-10-06 | L22: 수입 신고 항목·적합성 성명·중문 SDS/라벨 | M22: CIRS 해설 경유 | N22: 공식 출처·요약 확인
A23: SRC-018 | B23: GB 15603-2022 危险化学品仓库储存通则 | C23: 国家市场监督管理总局·国家标准化管理委员会 | D23: 강제 국가표준 | E23: 공식 | F23: 전국 | G23: 2022-12-29 | H23: 2023-07-01 | I23: 현행 | J23: https://www.cirs-group.com/cn/chemicals/gb-15603-2022-wei-xian-hua-xue-pin-cang-ku-chu-cun-tong-ze-fa-bu-2023-nian-7-yue-1-ri-shi-shi | K23: 2026-10-06 | L23: 저장 금기(혼재 금지)·입출고·응급 | M23: 표준 원문 구매·열람 필요 | N23: 공식 출처·요약 확인
A24: SRC-019 | B24: 应急管理部等10部门 2026年第3号公告 (危险化学品目录 5종 추가) | C24: 应急管理部 등 | D24: 공고 | E24: 공식 | F24: 전국 | G24: 2026-04-16 | H24: 2026-04-16 | I24: 현행 | J24: https://chemical.chemlinked.com/database/view/2656 | K24: 2026-10-06 | L24: 목록(2015판) 갱신 방식 | M24: Y·Sc·La 전구체 해당 여부는 별도 판정 | N24: 공식 출처·요약 확인
A25: SRC-020 | B25: 中华人民共和国公司法 (2023修订) 및 국무원 등록자본 관리 규정 | C25: 全国人大常委会·国务院 | D25: 법률·행정법규 | E25: 공식 | F25: 전국 | G25: 2023-12-29 | H25: 2024-07-01 | I25: 현행 | J25: https://paper.people.com.cn/rmrbwap/html/2024-07/02/nw.D110000renmrb_20240702_1-15.htm | K25: 2026-10-06 | L25: 5년 내 납입·법정대표인(이사/경리)·감사 생략 | N25: 공식 출처·요약 확인
A26: SRC-021 | B26: 外商投资准入特别管理措施（负面清单）（2024年版） | C26: 国家发展改革委·商务部 | D26: 목록 | E26: 공식 | F26: 전국 | G26: 2024-09 | H26: 2024-11-01 | I26: 현행 (신판 여부 확인) | J26: https://www.ndrc.gov.cn/xxgk/jd/jd/202409/t20240907_1392878.html | K26: 2026-10-06 | L26: 제한 29항목, 제조업 제한 전면 폐지 | M26: 화학품 도매가 목록에 없음은 원문 대조 필요 | N26: 공식 출처·요약 확인
A27: SRC-022 | B27: 중국 아포스티유 협약 가입(2023-11-07 발효) | C27: 中华人民共和国外交部 | D27: 공보 | E27: 공식 | F27: 전국 | G27: 2023-10-23 | H27: 2023-11-07 | I27: 현행 | J27: https://www.mfa.gov.cn/web/wjbxw_673019/202310/t20231023_11165858.shtml | K27: 2026-10-06 | L27: 영사 인증 → 아포스티유 | N27: 공식 출처·요약 확인
A28: SRC-023 | B28: 해외직접투자 신고 (외국환거래법·외국환거래규정) | C28: 외국환은행·언론 해설 | D28: 국내 규정 해설 | E28: 비공식 | F28: 한국 | G28: - | H28: - | I28: 현행 | J28: https://www.etoday.co.kr/news/view/1619152 | K28: 2026-10-06 | L28: 사전 신고·송금/증권취득 보고·2025 변경신고 사후화 | M28: 지정거래 외국환은행 확인 | N28: 언론·기타
A29: SRC-024 | B29: 2025년 무석시 비사영 단위 평균임금 147,293 CNY | C29: 언론(扬子晚报) 경유 통계 | D29: 통계 보도 | E29: 비공식 | F29: 무석시 | G29: 2026 | H29: - | I29: - | J29: https://www.yzwb.net/news/jiangsu/202607/t20260716_372860.html | K29: 2026-10-06 | L29: 인건비 가정 근거 | M29: 통계국 원자료 대조 | N29: 언론·기타
A30: SRC-025 | B30: 2025년 강소성 사회보험 납부기수 상한 24,762 / 하한 4,952 CNY/월 | C30: 国家税务总局江苏省税务局(검색 요약) | D30: 공고 | E30: 공식 | F30: 강소성 | G30: 2025 | H30: 2025-01-01 | I30: 2025년 기준 (2026년 기수 미확인) | J30: https://jiangsu.chinatax.gov.cn/art/2026/1/9/art_8274_1695385.html | K30: 2026-10-06 | L30: 사회보험 기수 | M30: 2026년 기수 공고 확인 필요 | N30: 공식 출처·요약 확인
A31: SRC-026 | B31: CNY/KRW 환율 1 CNY = 204 KRW (2026-09-01) | C31: XE 환율 (검색 요약) | D31: 시장 환율 | E31: 비공식 | F31: - | G31: 2026-09-01 | H31: - | I31: - | J31: https://xe.soft9.us/convert/cny-to-krw | K31: 2026-10-06 | L31: 환산 가정 | M31: 의사결정 시점 고시환율로 교체 | N31: 언론·기타
A32: SRC-027 | B32: 长鑫存储 등록 주소 (合肥经开区空港工业园兴业大道388号) | C32: 언론·기업정보 (검색 요약) | D32: 기업 정보 | E32: 비공식 | F32: 허페이 | G32: - | H32: - | I32: - | J32: https://www.cls.cn/detail/2331445 | K32: 2026-10-06 | L32: 고객 위치 | M32: 공장 위치는 고객 확인 | N32: 언론·기타
A33: SRC-028 | B33: 长江存储 주소 (武汉东湖新技术开发区未来三路88号) | C33: 언론·기업정보 (검색 요약) | D33: 기업 정보 | E33: 비공식 | F33: 우한 | G33: - | H33: - | I33: - | J33: https://www.ithome.com/0/913/335.htm | K33: 2026-10-06 | L33: 고객 위치 | N33: 언론·기타
A34: SRC-029 | B34: SK海力士 无锡 (新吴区) 공장 | C34: 언론 (검색 요약) | D34: 기업 정보 | E34: 비공식 | F34: 무석 | G34: - | H34: - | I34: - | J34: https://tech.ifeng.com/c/8t4IS42CqqC | K34: 2026-10-06 | L34: 고객 위치 | M34: 정확한 반입 주소는 고객 확인 | N34: 언론·기타
A35: SRC-030 | B35: 扬子江国际化学工业园 — 위험화학품 부두·보세 위험품 창고 | C35: 扬子晚报 | D35: 언론 | E35: 비공식 | F35: 장자강 | G35: 2025-10-09 | H35: - | I35: - | J35: https://www.yzwb.net/news/jiangsu/suzhou/202510/t20251009_274315.html | K35: 2026-10-06 | L35: 부두 5개·컨테이너 부두 2개·보세 위험품 창고 | M35: 취급 품목은 운영사 확인 | N35: 언론·기타
A36: SRC-031 | B36: 上海市危险化学品安全管理办法 | C36: 上海市人民政府 | D36: 지방정부 규장 | E36: 공식 | F36: 상하이 | G36: 2023-07-14 | H36: 2023 | I36: 현행 | J36: https://www.shanghai.gov.cn/xxzfgzwj/20230714/bb4d7f393a07460dba9a6ca6952808b5.html | K36: 2026-10-06 | L36: 상하이 경영·저장 관리 | N36: 공식 출처·요약 확인
A37: SRC-032 | B37: 上海 危险化学品经营（仓储）许可 新增品名 申请 指引 | C37: 上海市应急管理局 | D37: 업무 안내 | E37: 공식 | F37: 상하이 | G37: 2026 | H37: - | I37: 현행 | J37: https://yjglj.sh.gov.cn/cmsres/f5/f5b6c42ed8f445139addf137cc66d4f4/41ec57d5581db3a1f595d4f1a8f907a2.pdf | K37: 2026-10-06 | L37: 창고 품목 추가 절차 | N37: 공식 출처·요약 확인
A38: SRC-033 | B38: 浙江省 化工园区 (宁波石化·中国化工新材料(嘉兴)·平湖独山港 등) | C38: 前瞻产业研究院 등 | D38: 업계 자료 | E38: 비공식 | F38: 저장성 | G38: 2022 | H38: - | I38: - | J38: https://www.qianzhan.com/analyst/detail/220/220307-55693c0d.html | K38: 2026-10-06 | L38: 후보 원구 명칭 | M38: 성 정부 인정 명단 대조 필요 | N38: 언론·기타
A39: SRC-034 | B39: 安徽省 化工园区 2批 39곳 인정 / 위험등급 공고 | C39: 安徽省应急管理厅 (검색 요약) | D39: 공고 | E39: 공식 | F39: 안후이성 | G39: 2025-03-06 | H39: - | I39: - | J39: https://ahccci.huainan.gov.cn/group4/M00/0F/91/rB40qWfKTXKABLSFAAGhft5x_xU539.pdf | K39: 2026-10-06 | L39: 인정 원구 수 | M39: 허페이 원구 포함 여부 미확인 | N39: 공식 출처·요약 확인
A40: SRC-035 | B40: 위험화학품 경영허가 심사기한 20 영업일(자유무역시험구 무저장 고지승낙 15 영업일) 사례 | C40: 지방정부 (검색 요약) | D40: 업무 안내 | E40: 공식 | F40: 일부 지역 | G40: - | H40: - | I40: - | J40: https://www.sz.gov.cn/zfgb/2025/gb1390/content/post_12464094.html | K40: 2026-10-06 | L40: 처리기한 | M40: 강소성·무석 기한은 별도 확인 | N40: 공식 출처·요약 확인
A41: SRC-036 | B41: 신규화학물질 식별정보 보호(기간·연장 최대 5년) | C41: ChemLinked (생태환경부 공고 해설) | D41: 전문가 해설 | E41: 비공식 | F41: 전국 | G41: - | H41: - | I41: - | J41: https://chemical.chemlinked.com/news/chemical-news/china-mee-allows-extension-for-cbi-non-disclosure-under-mee-order-no12 | K41: 2026-10-06 | L41: 정보보호(명칭·CAS 비공개) | N41: 전문가 자료
A42: SRC-037 | B42: 배당 원천징수 10%(조약 시 인하)·배당 재투자 세액공제 10%(2025~2028) | C42: Fieldfisher | D42: 전문가 해설 | E42: 비공식 | F42: 전국 | G42: - | H42: 2025-01-01 | I42: - | J42: https://www.fieldfisher.com/zh-cn/locations/china/见解/有哪些税收优惠政策 | K42: 2026-10-06 | L42: 이익 회수 | M42: 한중 조세조약 세율은 원문 확인 | N42: 전문가 자료
A43: SRC-038 | B43: 苏州 무저장 위험화학품 경영허가 장소 요건 (업체 안내) | C43: 등록대행 업체 | D43: 업체 자료 | E43: 비공식 | F43: 쑤저우 | G43: - | H43: - | I43: - | J43: http://kszhuce8.com/nd.jsp?id=1200 | K43: 2026-10-06 | L43: 사무 장소 요건 | M43: 신뢰도 낮음 — 참고만 | N43: 언론·기타
A44: SRC-039 | B44: 省政府关于公布江苏省化工园区认定复核通过名单（第二批）(苏政发〔2023〕115号) | C44: 江苏省人民政府 | D44: 공고 | E44: 공식 | F44: 강소성 | G44: 2023 | H44: - | I44: 현행 | J44: https://www.waizi.org.cn/policy/210128.html | K44: 2026-10-06 | L44: 2차 인정 명단 | M44: 명단 본문 미확보 — 기관 확인 | N44: 공식 출처·요약 확인
A45: SRC-040 | B45: 简易登记 시험자료 요건(중국 공시생물 생태독성 시험 포함) | C45: 생태환경부 지침 (검색 요약) | D45: 지침 | E45: 공식 | F45: 전국 | G45: 2020 | H45: 2021-01-01 | I45: 현행 (개정 확인) | J45: https://www.mee.gov.cn/ywgz/gtfwyhxpgl/hxphjgl/zcfgybzgf/202011/t20201120_808952.shtml | K45: 2026-10-06 | L45: 간이등록 자료·중국 내 시험 | N45: 공식 출처·요약 확인

Sheet 04_EvidenceRaw
A1: 04_EvidenceRaw | 근거 원자료
A2: 원문 핵심 구절은 짧게(검색 요약에서 확인된 문구). '(요약)' 표시는 원문 문구가 아닌 요약
A3: 조사 기준일 2026-10-06 · 단위·상태는 각 열 머리글 참조
A5: 근거 ID | B5: 출처 ID | C5: 조사 질문 | D5: 원문 핵심 구절·원자료 | E5: 한국어 해석 | F5: 적용 대상 | G5: 적용 조건 | H5: 확인·추정 구분 | I5: 연결 제품·도시·허가 | J5: PPT 페이지
A6: EVD-001 | B6: SRC-001 | C6: 해외 제조자가 등록 신청인이 될 수 있나 (현행) | D6: 境外企业…可以作为申请人…指定在中国境内依法登记…代理人…共同履行 | E6: 현행 12호령: 해외 생산자도 중국 내 대리인을 지정하면 신청 가능 | F6: 해외 생산·무역 기업 | G6: 대리인이 함께 의무·책임 부담 | H6: 공식 출처·요약 확인 | I6: 등록 주체·G안 | J6: 05,10
A7: EVD-002 | B7: SRC-004 | C7: 개정안에서 신청 주체가 바뀌나 | D7: 仅境内…从事新化学物质生产或者进口的企业…作为申请人 (요약) | E7: 개정 초안: 중국 내 생산·수입 기업만 신청인. 해외 기업은 자료 제공만 | F7: 신규화학물질 등록 신청인 | G7: 개정안 확정 시 (현재 초안 확인) | H7: 공식 출처·요약 확인 | I7: 등록 주체·TC 법인 필요성 | J7: 02,05,10,23
A8: EVD-003 | B8: SRC-005 | C8: 备案 제도와 연말 기한 | D8: 自2026年8月15日起，停止办理新化学物质环境管理备案…于2026年12月31日前…申请取得登记证 | E8: 2026-08-15부터 备案(소량 신고) 접수 중단, 기존 备案 보유자는 12-31까지 등록증 취득 | F8: 기존 备案 보유자 | G8: 제품이 备案으로 수입돼 왔다면 적용 | H8: 공식 출처·요약 확인 | I8: 연말 기한 | J8: 02,05,26
A9: EVD-004 | B9: SRC-005 | C9: 备案 대상 물질의 전환 심사 방식 | D9: 参照简易登记程序和时限受理并审批 | E9: 1톤 미만 등 종전 备案 대상은 간이등록 절차·기한을 준용해 심사 | F9: 신규화학물질(소량) | G9: 제출: 신청표·증명자료·보유 위해성 정보 | H9: 공식 출처·요약 확인 | I9: 등록 일정 | J9: 10,26
A10: EVD-005 | B10: SRC-008 | C10: 기존 등록증의 효력 | D10: 原登记证继续有效；登记证载明事项发生变化…重新申请 (요약) | E10: 기존 등록증은 유효, 기재 사항이 바뀌면 새 규정으로 재신청 | F10: 기존 등록증 보유자 | G10: 주체 변경 = 기재 사항 변경으로 볼 가능성 | H10: 전문가 자료 | I10: 등록증 이관 | J10: 10,23
A11: EVD-006 | B11: SRC-040 | C11: 간이등록 시험자료 | D11: 生态毒理学测试报告应当包括使用中华人民共和国的供试生物…完成的测试数据 | E11: 간이등록 생태독성 자료에 중국 공시생물로 수행한 시험 포함 필요 | F11: 1~10 t/년 신규물질 | G11: 한국 시험자료만으로는 부족할 가능성 | H11: 공식 출처·요약 확인 | I11: 한국 시험자료 활용 | J11: 05,10
A12: EVD-007 | B12: SRC-036 | C12: 구조정보 비공개 | D12: 申请保护…标识信息…仅体现通用名 (요약) | E12: 명칭·CAS·구조식 보호 신청 가능, 승인 시 공시·명록에 일반명만 표시(기간 제한) | F12: 등록 신청인 | G12: 필요성 설명서 제출·기간 만료 시 공개 | H12: 전문가 자료 | I12: IP | J12: 10,23
A13: EVD-008 | B13: SRC-009 | C13: 위험화학품 경영 허가제 | D13: 国家对危险化学品经营（包括仓储经营）实行许可制度。未经许可…不得经营 | E13: 위험화학품 판매(창고업 포함)는 허가 필요 | F13: 위험화학품 판매자 | G13: 목록 해당 물질 | H13: 공식 출처·요약 확인 | I13: B·C·D안 경영허가 | J13: 07,11
A14: EVD-009 | B14: SRC-009 | C14: 생산기업 예외 | D14: 生产企业在其厂区范围内销售本企业生产的危险化学品，不需要取得…经营许可 | E14: 자기 공장에서 만든 제품을 공장 안에서 파는 경우만 경영허가 면제 | F14: 생산기업 | G14: 수입·유통 법인에는 해당 없음 | H14: 공식 출처·요약 확인 | I14: 생산허가 가설 | J14: 05,07
A15: EVD-010 | B15: SRC-009 | C15: 수입 위험화학품 | D15: 进口的危险化学品的储存、使用、经营、运输的安全管理，依照本法 | E15: 수입품도 저장·사용·경영·운송은 같은 법 적용. 수출입 자체는 무역 법령 | F15: 수입자 | H15: 공식 출처·요약 확인 | I15: 수입 | J15: 07,11
A16: EVD-011 | B16: SRC-009 | C16: 생산 안전허가 대상 | D16: 危险化学品生产企业…取得危险化学品安全生产许可 (요약) | E16: 안전생산허가는 '생산기업' 대상. 수입·판매만 하는 기업 대상 규정은 확인되지 않음 | F16: 생산기업 | G16: 충진·분장 등은 지역별 '분장·충진 경영' 또는 생산 판단 필요 | H16: 공식 출처·요약 확인 | I16: 생산허가 가설 | J16: 05,07
A17: EVD-012 | B17: SRC-010 | C17: 경영허가 기본 조건 | D17: 主要负责人和安全生产管理人员…经考核合格…有专职安全生产管理人员…安全管理制度…应急预案 (요약) | E17: 책임자·안전관리자 교육·시험 합격, 전담 안전관리자, 규정·응급계획, 적합한 사무 장소 | F17: 모든 경영기업 | G17: 저장 시 추가 요건 | H17: 공식 출처·요약 확인 | I17: 인력·시설 | J17: 11,12,24
A18: EVD-013 | B18: SRC-009 | C18: 저장 시설이 있는 경우 추가 요건 | D18: 储存设施建立在地方政府规划的专门区域…安全评价…专职安全管理人员 (요약) | E18: 저장 시설은 지방정부가 정한 전용 구역(화공원구 등)에 있어야 하고 안전평가 필요 | F18: 저장 경영 | G18: 자체·임차 창고(C·D안) | H18: 공식 출처·요약 확인 | I18: 창고 입지 | J18: 11,12,19
A19: EVD-014 | B19: SRC-011 | C19: 무석의 경영 방식 구분 | D19: 经营方式分为：无储存经营、有储存经营、租赁储存经营、加油站经营 | E19: 무석은 무저장·유저장·임차저장 경영을 별도 유형으로 운영 | F19: 무석 신청기업 | G19: 임차저장 세부 조건 원문 확인 | H19: 공식 출처·요약 확인 | I19: B·C안 무석 | J19: 11,15
A20: EVD-015 | B20: SRC-011 | C20: 무저장 경영 정의 | D20: 无储存经营…仅限于票据往来经营 (요약) | E20: 무저장 = 자체 저장시설 없이 서류(계약·세금계산서)로만 거래 | F20: 무저장 신청기업 | G20: 사무 장소에 위험화학품 보관 금지 | H20: 공식 출처·요약 확인 | I20: B안 | J20: 11
A21: EVD-016 | B21: SRC-035 | C21: 경영허가 처리기한 | D21: 审批时限由30个工作日压减至20个工作日…无储存…告知承诺…15个工作日 (요약) | E21: 일부 지역 사례: 20 영업일, 자유무역시험구 무저장 고지승낙 15 영업일 | F21: 경영허가 | G21: 강소성·무석 기한 별도 확인 | H21: 공식 출처·요약 확인 | I21: 일정 | J21: 11,26
A22: EVD-017 | B22: SRC-010 | C22: 허가 유효기간 | D22: 有效期为3年 (요약) | E22: 경영허가 유효기간 3년, 만료 3개월 전 연장 신청 | F22: 경영허가 | H22: 공식 출처·요약 확인 | I22: 유지 비용 | J22: 11
A23: EVD-018 | B23: SRC-016 | C23: 수입기업 위험화학품 등록 | D23: 危险化学品生产企业、进口企业…进行登记 (요약) | E23: 목록 위험화학품 수입기업은 첫 수입 전 응급관리부 화학품등록센터에 등록 | F23: 수입자 | G23: 목록 해당 물질 | H23: 공식 출처·요약 확인 | I23: 수입자 역할 | J23: 07,11
A24: EVD-019 | B24: SRC-017 | C24: 수입 통관 서류 | D24: 如实填报危险类别、包装类别、UN编号…符合性声明…中文危险公示标签、中文安全数据单 | E24: 수입 신고 시 위험 분류·UN번호, 적합성 성명, 중문 라벨·SDS 제출 | F24: 수입 신고인 | G24: 2021-01-10 시행 | H24: 공식 출처·요약 확인 | I24: 통관 | J24: 07,24
A25: EVD-020 | B25: SRC-013 | C25: 강소성 인정 화공원구 | D25: 南京江北新材料科技园…江阴临港化工园区…锡山经济技术开发区新材料产业园…宜兴市新材料产业园…江苏扬子江国际化学工业园…江苏高科技氟化学工业园（江苏常熟新材料产业园）… 等23家 | E25: 강소성 1차 인정 화공원구 23곳 (무석 3·쑤저우 2·창저우·전장·난징·난퉁 3·양저우·타이저우 2 등) | F25: 강소성 | G25: 2차 명단 별도 | H25: 공식 출처·요약 확인 | I25: 창고 입지 | J25: 13,14
A26: EVD-021 | B26: SRC-030 | C26: 장자강 위험품 물류 기반 | D26: 5个危化品散货码头、2个危化品集装箱码头…危化品保税仓库 (요약) | E26: 장자강 扬子江国际化学工业园에 위험화학품 부두·보세 위험품 창고가 있다는 보도 | F26: 장자강 | G26: 취급 품목·4.2/4.3류 수용 여부 미확인 | H26: 언론·기타 | I26: SITE-005 | J26: 16
A27: EVD-022 | B27: SRC-020 | C27: 등록자본 납입 | D27: 有限责任公司…自公司成立之日起五年内缴足 | E27: 유한회사 등록자본은 설립 후 5년 내 납입. 일반 무역법인의 법정 최저자본은 확인되지 않음 | F27: 신설 법인 | H27: 공식 출처·요약 확인 | I27: 자본 | J27: 09,25
A28: EVD-023 | B28: SRC-020 | C28: 기관 구성 | D28: 法定代表人…由代表公司执行公司事务的董事或者经理担任…规模较小…可以不设监事 | E28: 법정대표인은 이사 또는 경리, 소규모 회사는 감사 1명 또는 전원 동의 시 생략 | F28: 신설 법인 | H28: 공식 출처·요약 확인 | I28: 인력 | J28: 09,24
A29: EVD-024 | B29: SRC-021 | C29: 외국인 투자 제한 | D29: 限制措施由31条减至29条…制造业…全面取消 (요약) | E29: 2024 네거티브리스트 29개 항목. 화학품 도매는 목록에 없는 것으로 파악(원문 대조 필요) | F29: 외국인 투자 무역법인 | H29: 공식 출처·요약 확인 | I29: 법인 설립 | J29: 09
A30: EVD-025 | B30: SRC-022 | C30: 문서 인증 | D30: 仅需办理…附加证明书…无需…领事认证 | E30: 한국 서류는 아포스티유로 대체(영사 인증 불필요) | F30: 한국 본사 서류 | G30: 한국도 협약국 | H30: 공식 출처·요약 확인 | I30: 설립 일정 | J30: 09
A31: EVD-026 | B31: SRC-023 | C31: 한국 측 신고 | D31: 1달러라도…외국환은행장에 사전 신고 | E31: 해외직접투자는 송금 전 지정거래 외국환은행 신고 | F31: TC 본사 | H31: 언론·기타 | I31: 설립 절차 | J31: 09
A32: EVD-027 | B32: SRC-024 | C32: 무석 평균임금 | D32: 2025年无锡市城镇非私营单位在岗职工年平均工资为147293元 | E32: 무석 비사영 평균임금 147,293 CNY/년 | F32: 인건비 가정 | G32: 직무별 시장급여 아님 | H32: 언론·기타 | I32: COST | J32: 25
A33: EVD-028 | B33: SRC-018 | C33: 창고 저장 기준 | D33: 规定了…储存的基本要求…危险化学品存储禁忌表 (요약) | E33: GB 15603-2022: 혼재 금지표·입출고·응급 기준(2023-07-01 시행) | F33: 창고 | G33: 4.2·4.3류 적용 조항 원문 확인 | H33: 공식 출처·요약 확인 | I33: 창고 | J33: 12
A34: EVD-029 | B34: SRC-027 | C34: CXMT 위치 | D34: 合肥市经济技术开发区空港工业园兴业大道388号 | E34: CXMT 등록 주소: 허페이 경제기술개발구 | F34: 고객 | G34: 등록 주소 ≠ 반입 위치 가능 | H34: 언론·기타 | I34: CUST-01 | J34: 04,13,20
A35: EVD-030 | B35: SRC-028 | C35: YMTC 위치 | D35: 武汉东湖新技术开发区未来三路88号 | E35: YMTC 주소: 우한 동호고신구 | F35: 고객 | H35: 언론·기타 | I35: CUST-03 | J35: 04,20
A36: EVD-031 | B36: SRC-029 | C36: SK하이닉스 우시 위치 | D36: 无锡…新吴区 (요약) | E36: SK하이닉스 우시 공장: 무석 신오구(정확한 주소는 고객 확인) | F36: 고객 | H36: 언론·기타 | I36: CUST-02 | J36: 04,13
A37: EVD-032 | B37: SRC-019 | C37: 위험화학품 목록 갱신 | D37: 2026年第3号公告…新增5种…7月31日前完成许可登记 (요약) | E37: 위험화학품 목록(2015판)은 공고로 추가됨 → 미등재 물질도 위험성 판정 필요 | F37: 전 제품 | H37: 공식 출처·요약 확인 | I37: 제품 분류 | J37: 06
A38: EVD-033 | B38: SRC-015 | C38: 강소성 화공 산업 목록 | D38: 2026年1月24日起实施，有效期至2031年1月23日 | E38: 제조(F안) 검토 시 강소성 제한·도태 목록 확인 필요 | F38: 제조 활동 | H38: 공식 출처·요약 확인 | I38: F안 | J38: 08
A39: EVD-034 | B39: SRC-026 | C39: 환율 | D39: 1 CNY = 204 KRW (2026-09-01) | E39: 분석용 환율 1 CNY = 204 KRW | F39: 비용 환산 | G39: 결정 시점 갱신 | H39: 언론·기타 | I39: FX | J39: 25
A40: EVD-035 | B40: SRC-037 | C40: 이익 회수 | D40: 股息…20%…减按10%…协定…可低至5% (요약) | E40: 배당 원천징수 10%, 조약으로 인하 가능(한중 세율 확인) | F40: 배당 | H40: 전문가 자료 | I40: 자금 회수 | J40: 25
A41: EVD-036 | B41: SRC-025 | C41: 사회보험 기수 | D41: 上限24762元，下限4952元 (2025) | E41: 강소성 2025 사회보험 기수 상한·하한 | F41: 인건비 | G41: 2026 기수 미확인 | H41: 공식 출처·요약 확인 | I41: COST | J41: 25

Sheet 05_Materials
A1: 05_Materials | 제품 입력자료·규제 판단
A2: 제품 정보가 제공되지 않아 CAS·위험등급을 임의로 넣지 않음. 시나리오 A~D로 분석
A3: 조사 기준일 2026-10-06 · 단위·상태는 각 열 머리글 참조
A5: 제품 ID | B5: 제품 코드·명 | C5: 화학명 | D5: CAS | E5: 조성·용매 | F5: IECSC 등재 | G5: 신규물질 판단 | H5: 위험화학품 판단 | I5: 운송 분류·UN | J5: 물성·보관 조건 | K5: 연간 물량 | L5: 기존 등록·备案 | M5: 자료 소유권 | N5: 정보 상태 | O5: 추가 필요 자료 | P5: 근거 ID
A6: MAT-01 | B6: 이트륨(Y) 전구체 (제품명 미제공) | C6: 미제공 | D6: 미제공 | E6: 미제공 | F6: 확인 필요 (IECSC 검색) | G6: 시나리오 A/B 또는 C/D | H6: 확인 필요 (목록·분류 판정) | I6: 확인 필요 (UN번호) | J6: 확인 필요 (자연발화·수분반응 여부) | K6: 미제공 | L6: 확인 필요 (备案 여부) | M6: 확인 필요 | N6: 정보 없음 | O6: SDS(국문/영문), CAS, 조성, 연간 수입량, 기존 备案·등록 번호, 시험보고서 목록 | P6: EVD-032, EVD-003
A7: MAT-02 | B7: 스칸듐(Sc) 전구체 (제품명 미제공) | C7: 미제공 | D7: 미제공 | E7: 미제공 | F7: 확인 필요 | G7: 시나리오 A~D | H7: 확인 필요 | I7: 확인 필요 | J7: 확인 필요 | K7: 미제공 | L7: 확인 필요 | M7: 확인 필요 | N7: 정보 없음 | O7: 동일 | P7: EVD-032, EVD-003
A8: MAT-03 | B8: 란타늄(La) 전구체 (제품명 미제공) | C8: 미제공 | D8: 미제공 | E8: 미제공 | F8: 확인 필요 | G8: 시나리오 A~D | H8: 확인 필요 | I8: 확인 필요 | J8: 확인 필요 | K8: 미제공 | L8: 확인 필요 | M8: 확인 필요 | N8: 정보 없음 | O8: 동일 | P8: EVD-032, EVD-003
A9: MAT-04 | B9: CpZr 계열 (후속 검토) | C9: 미제공 | D9: 미제공 | E9: 미제공 | F9: 확인 필요 | G9: 시나리오 A~D | H9: 확인 필요 | I9: 확인 필요 | J9: 확인 필요 | K9: 생산계획 자료 별도 | L9: 확인 필요 | M9: 확인 필요 | N9: 정보 없음 | O9: 동일 + 고객별 수입 구조 | P9: EVD-032, EVD-003
A12: 규제 시나리오
A13: 시나리오 | B13: 구분 | C13: 필요 등록·영업·보관·운송 | D13: 사업 영향
A14: A | B14: 신규 · 위험화학품 | C14: 등록 필요(간이/상규) + 수입기업 위험화학품 등록 + 경영허가 + 허가 창고·위험물 운송 | D14: 가장 무거움. 등록 신청 주체가 핵심 (개정 시 중국 수입기업)
A15: B | B15: 신규 · 비위험 | C15: 등록 필요 + 경영허가 불필요(목록 비해당·판정 근거 보관) + 일반 창고 가능(물성 확인) | D15: 등록 주체 문제만 남음
A16: C | B16: 기존 · 위험화학품 | C16: 등록 불필요 + 위험화학품 등록·경영허가·허가 창고·위험물 운송 | D16: 법인·허가·창고가 핵심
A17: D | B17: 기존 · 비위험 | C17: 등록·경영허가 불필요 + 일반 수입·판매 | D17: MP 또는 일반 무역법인도 가능
A19: 운송상 위험물(UN 분류)과 위험화학품 목록 해당 여부는 별개로 판정 — 둘 다 확인

Sheet 06_LegalMatrix
A1: 06_LegalMatrix | 법적 쟁점 매트릭스
A2: 국가 공통 규정과 성·시 집행 기준 구분. 결론은 근거 기반 판단이며 법률 의견이 아님
A3: 조사 기준일 2026-10-06 · 단위·상태는 각 열 머리글 참조
A5: 법적 쟁점 | B5: 국가·성·시 | C5: 관련 규정 | D5: 조문 | E5: 활동·품목 | F5: 의무·예외 | G5: 필요 자료 | H5: 담당 기관 | I5: 결론 | J5: 조건 | K5: 미확인 | L5: 근거 ID
A6: 신규화학물질 등록 신청 주체 (현행) | B6: 국가 | C6: 12호령 | D6: 신청인 조항 | E6: 신규물질 생산·수입 | F6: 해외 생산자 + 중국 대리인 가능 | G6: 대리 계약·신청서·시험자료 | H6: 생태환경부 고체·화학품 관리기술센터 | I6: 현행 규정상 TC 본사 + 대리인 신청 가능 | J6: 개정안 확정 전까지 | K6: 현재 적용 규정(개정 공포 여부) | L6: EVD-001
A7: 신규화학물질 등록 신청 주체 (개정안) | B7: 국가 | C7: 12호령 개정 초안 | D7: 신청인 조항 | E7: 동일 | F7: 중국 내 생산·수입 기업만 | G7: 해외 기업은 자료 제공 | H7: 생태환경부 | I7: 확정 시 중국 수입 법인(TC 법인·MP·고객) 명의 필요 | J7: 개정 최종본 | K7: 최종 공포·시행일 | L7: EVD-002
A8: 备案 중단·연말 전환 | B8: 국가 | C8: 환판고체함〔2026〕301호 | D8: - | E8: 기존 备案 물질 | F8: 2026-12-31까지 등록증 취득 | G8: 신청표·증명·위해성 정보 | H8: 생태환경부 | I8: 기존 备案 보유자에게 연말 기한 존재 | J8: 제품이 备案으로 수입돼 왔을 때 | K8: TC 제품 备案 보유자·번호 | L8: EVD-003
A9: 수입·판매만 할 때 생산허가 | B9: 국가 | C9: 위험화학품안전법 | D9: 제53조 외 | E9: 수입·판매 | F9: 생산허가는 생산기업 대상 | G9: - | H9: 응급관리부문 | I9: 단순 수입·판매에는 생산허가·생산설비 불필요 (근거 기반) | J9: 충진·소분 등 가공 없음 | K9: 지역별 '분장·충진' 해석 | L9: EVD-009, EVD-011
A10: 위험화학품 경영허가 | B10: 국가·시 | C10: 위험화학품안전법·55호령·무석 세칙 | D10: 제53·54조 | E10: 판매(무저장/임차저장/저장) | F10: 허가 필수, 생산기업 자사품 공장 내 판매 예외 | G10: 책임자·안전관리자 자격, 규정, 응급계획, 장소 | H10: 구·시 행정심사국/응급관리국 | I10: 수입·판매 법인은 경영허가 필요(위험화학품일 때) | J10: 목록 해당 | K10: 무석 신오구 세부 요건·기한 | L10: EVD-008, EVD-012, EVD-014
A11: 저장 시설 위치 | B11: 국가·성 | C11: 위험화학품안전법·강소성 화공원구 관리 | D11: 제54조 외 | E11: 자체·임차 저장 | F11: 지방정부 지정 전용구역 | G11: 안전평가·건설 안전심사 | H11: 응급관리부문·원구 | I11: 강소성 신규 저장은 인정 화공원구 내가 현실적 | J11: 자체·임차 창고 | K11: 무석 임차저장 세부 조건 | L11: EVD-013, EVD-020
A12: 수입기업 위험화학품 등록 | B12: 국가 | C12: 53호령(등록관리) | D12: - | E12: 목록 물질 수입 | F12: 첫 수입 전 등록 | G12: SDS·라벨·분류보고 | H12: 응급관리부 화학품등록센터 | I12: 수입 명의자가 등록 | J12: 목록 해당 | K12: 신법 하위규정 정비 | L12: EVD-018
A13: 수입 통관 검사 | B13: 국가 | C13: 해관총서 2020-129호 | D13: - | E13: 위험화학품 수입 | F13: 위험 분류·UN번호 신고, 중문 라벨·SDS | G13: 적합성 성명·라벨·SDS | H13: 해관 | I13: 수입자가 중문 SDS·라벨 준비 | J13: 목록 해당 | K13: - | L13: EVD-019
A14: 한국 시험자료 사용 | B14: 국가 | C14: 등록 지침 | D14: - | E14: 간이·상규 등록 | F14: 중국 공시생물 생태독성 시험 필요 | G14: GLP 시험보고서 | H14: 생태환경부 | I14: 그대로 사용은 어려움(일부 보완 시험) | J14: 등록 유형별 | K14: 물질별 요구 시험 목록 | L14: EVD-006
A15: 외국인 독자 법인 | B15: 국가 | C15: 네거티브리스트 2024 | D15: - | E15: 화학품 도매 | F15: 제한 목록에 없음(파악) | G15: - | H15: 시장감독관리국 | I15: 100% 외자 무역법인 설립 가능(근거 기반) | J15: - | K15: 원문 대조 | L15: EVD-024

Sheet 07_PermitPaths
A1: 07_PermitPaths | 허가·등록 절차
A2: 현실 예상기간(주)은 분석 가정. 법정 처리기간은 확인된 경우만 기재
A3: 조사 기준일 2026-10-06 · 단위·상태는 각 열 머리글 참조
A5: 운영 구조 | B5: 절차·허가명 | C5: 신청 주체 | D5: 관할 | E5: 선행 조건 | F5: 제출 자료 | G5: 시설 | H5: 인력 | I5: 법정 처리기간 | J5: 현실 예상기간(주) | K5: 비용 | L5: 갱신·유지 | M5: 근거 ID
A6: 공통 | B6: 한국 해외직접투자 신고 | C6: TC 본사 | D6: 지정거래 외국환은행 | E6: - | F6: 신고서·사업계획 | G6: - | H6: - | I6: - | J6: 1 | K6: 수수료 수준 | L6: 변경 시 사후 신고 | M6: EVD-026
A7: 공통 | B7: 법인 설립 등기(营业执照) | C7: TC 본사(투자자) | D7: 구 시장감독관리국 | E7: 주소(임대계약)·서류 아포스티유 | F7: 정관·투자자 증명·법정대표인 등 | G7: 사무실 | H7: 법정대표인·이사·(감사) | I7: 기관 확인 | J7: 5 | K7: 대행비 견적 필요 | L7: - | M7: EVD-022, EVD-025
A8: 공통 | B8: 은행 계좌·외환·세무·해관 등록 | C8: 중국 법인 | D8: 은행·세무국·해관 | E8: 营业执照 | F8: 인감·서류 | G8: - | H8: 재무 담당 | I8: 기관 확인 | J8: 3 | K8: 견적 필요 | L8: - | M8: 기관 확인 필요
A9: B·C·D | B9: 위험화학품 경영허가(무저장/임차저장/저장) | C9: 중국 법인 | D9: 무석 신오구 행정심사국(예상) | E9: 营业执照·장소·인력 자격 | F9: 신청서·규정·응급계획·자격증 | G9: 무저장: 사무실 / 저장: 허가 창고 | H9: 책임자·전담 안전관리자 | I9: 20 영업일(사례) | J9: 8 | K9: 견적 필요 | L9: 3년 | M9: EVD-012, EVD-016
A10: B·C·D | B10: 수입기업 위험화학품 등록 | C10: 중국 법인(수입 명의) | D10: 응급관리부 화학품등록센터 | E10: 경영 주체 확정 | F10: SDS·라벨·분류보고 | G10: - | H10: - | I10: 기관 확인 | J10: 4 | K10: 분류 감정비 견적 필요 | L10: 변경 시 | M10: EVD-018
A11: 공통 | B11: 신규화학물질 등록(간이) / 备案 전환 | C11: 현행: 해외 생산자+대리인 / 개정안: 중국 수입기업 | D11: 생태환경부 | E11: 물질 식별·시험자료 | F11: 신청표·시험보고서·위해성 정보 | G11: - | H11: - | I11: 간이등록 절차·기한 준용 | J11: 16 | K11: 시험·대행 견적 필요 | L11: - | M11: EVD-003, EVD-004, EVD-006
A12: C | B12: 임차 창고 안전생산관리협의·품목 추가 | C12: 중국 법인·창고 운영사 | D12: 응급관리부문 | E12: 허가 창고 확보 | F12: 협의서·품목 | G12: 허가 창고 | H12: - | I12: 기관 확인 | J12: 6 | K12: 견적 필요 | L12: - | M12: EVD-014
A13: D | B13: 자체 창고 건설(입지·안전·환경·소방) | C13: 중국 법인 | D13: 원구·응급·생태·소방 | E13: 원구 입주 승인 | F13: 안전평가·설계·환경평가 | G13: 자체 창고 | H13: 전담 인력 | I13: 기관 확인 | J13: 52 | K13: 견적 필요 | L13: - | M13: EVD-013

Sheet 08_CityComparison
A1: 08_CityComparison | 도시 관문·평가 점수
A2: 필수 관문 미통과·정보 부족 후보는 점수를 매기지 않음(점수 보류). 점수는 분석 가정(1~5)
A3: 조사 기준일 2026-10-06 · 단위·상태는 각 열 머리글 참조
L4: 인허가 경로 | M4: 적격 창고 | N4: 개시 일정 | O4: 고객·물류 | P4: 비용 | Q4: 인력·확장
K6: 가중치 세트 | L6: 인허가 경로 | M6: 적격 창고 | N6: 개시 일정 | O6: 고객·물류 | P6: 비용 | Q6: 인력·확장
K7: 기본(허가 우선 제안) | L7: 30 | M7: 20 | N7: 15 | O7: 15 | P7: 15 | Q7: 5 | R7: =SUM(L7:Q7) -> 100
K8: 속도 우선 | L8: 20 | M8: 15 | N8: 35 | O8: 15 | P8: 10 | Q8: 5 | R8: =SUM(L8:Q8) -> 100
K9: 비용 우선 | L9: 20 | M9: 15 | N9: 15 | O9: 10 | P9: 35 | Q9: 5 | R9: =SUM(L9:Q9) -> 100
A12: 도시 ID | B12: 성·직할시 | C12: 지급시 | D12: 구·현·현급시 | E12: 운영 구조 역할 | F12: 위도 | G12: 경도 | H12: G1 법인 설립 | I12: G2 무저장 경영 경로 | J12: G3 적격 창고 후보 | K12: 점수: 인허가 경로 | L12: 점수: 적격 창고 | M12: 점수: 개시 일정 | N12: 점수: 고객·물류 | O12: 점수: 비용 | P12: 점수: 인력·확장 | Q12: 종합(기본) | R12: 종합(속도 우선) | S12: 종합(비용 우선) | T12: 근거 충족 | U12: 판정 | V12: 이유 | W12: 근거 ID
A13: CITY-001 | B13: 강소성 | C13: 无锡(무석) | D13: 新吴区(신오구) | E13: 법인·영업 거점 (+무석 관할 원구 창고) | F13: 31.55 | G13: 120.37 | H13: 통과 | I13: 통과(세칙 공개) | J13: 조건부(江阴·锡山·宜兴 원구) | K13: 4 | L13: 3 | M13: 4 | N13: 5 | O13: 3 | P13: 4 | Q13: =IF(OR(ISNUMBER(SEARCH("미통과",J13)),COUNT(K13:P13)<6),"점수 보류",SUMPRODUCT(K13:P13,$L$7:$Q$7)/5) -> 76 | R13: =IF(OR(ISNUMBER(SEARCH("미통과",J13)),COUNT(K13:P13)<6),"점수 보류",SUMPRODUCT(K13:P13,$L$8:$Q$8)/5) -> 78 | S13: =IF(OR(ISNUMBER(SEARCH("미통과",J13)),COUNT(K13:P13)<6),"점수 보류",SUMPRODUCT(K13:P13,$L$9:$Q$9)/5) -> 72 | T13: 중 | U13: 강소성 1순위 · 조건부 추천 | V13: SK하이닉스 근접, 무석 세칙에 무저장·임차저장 유형 명시, 관할 내 인정 화공원구 3곳 | W13: EVD-014, EVD-020, EVD-031
A14: CITY-002 | B14: 강소성 | C14: 苏州(쑤저우) | D14: 工业园区(SIP) + 张家港(장자강, 현급시) | E14: 법인(SIP) + 장자강 보세·위험품 물류 | F14: 31.32 | G14: 120.72 | H14: 통과 | I14: 조건부(쑤저우 세칙 미확보) | J14: 조건부(扬子江国际化学工业园·常熟 원구) | K14: 3 | L14: 4 | M14: 3 | N14: 4 | O14: 3 | P14: 5 | Q14: =IF(OR(ISNUMBER(SEARCH("미통과",J14)),COUNT(K14:P14)<6),"점수 보류",SUMPRODUCT(K14:P14,$L$7:$Q$7)/5) -> 69 | R14: =IF(OR(ISNUMBER(SEARCH("미통과",J14)),COUNT(K14:P14)<6),"점수 보류",SUMPRODUCT(K14:P14,$L$8:$Q$8)/5) -> 68 | S14: =IF(OR(ISNUMBER(SEARCH("미통과",J14)),COUNT(K14:P14)<6),"점수 보류",SUMPRODUCT(K14:P14,$L$9:$Q$9)/5) -> 67 | T14: 중 | U14: 강소성 차선 · 조건부 | V14: 장자강 위험화학품 부두·보세 위험품 창고 보도, 인력·서비스 풍부 | W14: EVD-020, EVD-021
A15: CITY-003 | B15: 강소성 | C15: 常州(창저우) | D15: 新北区 滨江경개구 | E15: 중장기 자체시설(D안) 후보 | F15: 31.98 | G15: 119.9 | H15: 통과 | I15: 확인 필요 | J15: 조건부(滨江 新材料产业园) | K15: 3 | L15: 3 | M15: 3 | N15: 3 | O15: 4 | P15: 3 | Q15: =IF(OR(ISNUMBER(SEARCH("미통과",J15)),COUNT(K15:P15)<6),"점수 보류",SUMPRODUCT(K15:P15,$L$7:$Q$7)/5) -> 63 | R15: =IF(OR(ISNUMBER(SEARCH("미통과",J15)),COUNT(K15:P15)<6),"점수 보류",SUMPRODUCT(K15:P15,$L$8:$Q$8)/5) -> 62 | S15: =IF(OR(ISNUMBER(SEARCH("미통과",J15)),COUNT(K15:P15)<6),"점수 보류",SUMPRODUCT(K15:P15,$L$9:$Q$9)/5) -> 67 | T15: 하 | U15: 강소성 3순위 · 기관 확인 후 결정 | V15: 무석·난징 사이, 인정 원구 보유. 공개 운영 자료 부족 | W15: EVD-020
A16: CITY-004 | B16: 강소성 | C16: 镇江(전장) | D16: 镇江新区 | E16: 원구·항만 물류 후보 | F16: 32.18 | G16: 119.68 | H16: 통과 | I16: 확인 필요 | J16: 조건부(镇江新区新材料产业园) | L16: 3 | M16: 3 | N16: 2 | O16: 4 | P16: 3 | Q16: =IF(OR(ISNUMBER(SEARCH("미통과",J16)),COUNT(K16:P16)<6),"점수 보류",SUMPRODUCT(K16:P16,$L$7:$Q$7)/5) -> 점수 보류 | R16: =IF(OR(ISNUMBER(SEARCH("미통과",J16)),COUNT(K16:P16)<6),"점수 보류",SUMPRODUCT(K16:P16,$L$8:$Q$8)/5) -> 점수 보류 | S16: =IF(OR(ISNUMBER(SEARCH("미통과",J16)),COUNT(K16:P16)<6),"점수 보류",SUMPRODUCT(K16:P16,$L$9:$Q$9)/5) -> 점수 보류 | T16: 하 | U16: 보류 | V16: 그룹 과거 법인 언급은 내부 확인. 무석 고객과 거리 | W16: EVD-020
A17: CITY-005 | B17: 강소성 | C17: 南通(난퉁) | D17: 경개구·如东·如皋 | E17: 원구 창고 후보 | F17: 31.95 | G17: 120.95 | H17: 통과 | I17: 확인 필요 | J17: 조건부(3개 원구) | L17: 3 | M17: 3 | N17: 2 | O17: 4 | P17: 3 | Q17: =IF(OR(ISNUMBER(SEARCH("미통과",J17)),COUNT(K17:P17)<6),"점수 보류",SUMPRODUCT(K17:P17,$L$7:$Q$7)/5) -> 점수 보류 | R17: =IF(OR(ISNUMBER(SEARCH("미통과",J17)),COUNT(K17:P17)<6),"점수 보류",SUMPRODUCT(K17:P17,$L$8:$Q$8)/5) -> 점수 보류 | S17: =IF(OR(ISNUMBER(SEARCH("미통과",J17)),COUNT(K17:P17)<6),"점수 보류",SUMPRODUCT(K17:P17,$L$9:$Q$9)/5) -> 점수 보류 | T17: 하 | U17: 보류 | V17: 원구 다수, 장강 북안 — 무석 반입 동선 확인 필요 | W17: EVD-020
A18: CITY-006 | B18: 강소성 | C18: 南京(난징) | D18: 江北新区 (江北新材料科技园) | E18: 행정·원구 후보 | F18: 32.26 | G18: 118.85 | H18: 통과 | I18: 통과(세칙 공개) | J18: 조건부(江北 원구) | K18: 3 | L18: 3 | M18: 3 | N18: 2 | O18: 3 | P18: 4 | Q18: =IF(OR(ISNUMBER(SEARCH("미통과",J18)),COUNT(K18:P18)<6),"점수 보류",SUMPRODUCT(K18:P18,$L$7:$Q$7)/5) -> 58 | R18: =IF(OR(ISNUMBER(SEARCH("미통과",J18)),COUNT(K18:P18)<6),"점수 보류",SUMPRODUCT(K18:P18,$L$8:$Q$8)/5) -> 58 | S18: =IF(OR(ISNUMBER(SEARCH("미통과",J18)),COUNT(K18:P18)<6),"점수 보류",SUMPRODUCT(K18:P18,$L$9:$Q$9)/5) -> 59 | T18: 중 | U18: 보류(대안) | V18: 세칙 공개·원구 보유. 고객(무석·허페이) 중간 위치 | W18: EVD-020, SRC-012
A19: CITY-007 | B19: 강소성 | C19: 扬州(양저우) | D19: 仪征 (扬州化学工业园区) | E19: 원구 창고 후보 | F19: 32.27 | G19: 119.18 | H19: 통과 | I19: 확인 필요 | J19: 조건부 | L19: 3 | M19: 3 | N19: 2 | O19: 4 | P19: 3 | Q19: =IF(OR(ISNUMBER(SEARCH("미통과",J19)),COUNT(K19:P19)<6),"점수 보류",SUMPRODUCT(K19:P19,$L$7:$Q$7)/5) -> 점수 보류 | R19: =IF(OR(ISNUMBER(SEARCH("미통과",J19)),COUNT(K19:P19)<6),"점수 보류",SUMPRODUCT(K19:P19,$L$8:$Q$8)/5) -> 점수 보류 | S19: =IF(OR(ISNUMBER(SEARCH("미통과",J19)),COUNT(K19:P19)<6),"점수 보류",SUMPRODUCT(K19:P19,$L$9:$Q$9)/5) -> 점수 보류 | T19: 하 | U19: 보류 | V19: 공개 자료 부족 | W19: EVD-020
A20: CITY-008 | B20: 강소성 | C20: 泰州(타이저우) | D20: 泰兴·滨江 | E20: 원구 창고 후보 | F20: 32.17 | G20: 120.02 | H20: 통과 | I20: 확인 필요 | J20: 조건부 | L20: 3 | M20: 3 | N20: 2 | O20: 4 | P20: 3 | Q20: =IF(OR(ISNUMBER(SEARCH("미통과",J20)),COUNT(K20:P20)<6),"점수 보류",SUMPRODUCT(K20:P20,$L$7:$Q$7)/5) -> 점수 보류 | R20: =IF(OR(ISNUMBER(SEARCH("미통과",J20)),COUNT(K20:P20)<6),"점수 보류",SUMPRODUCT(K20:P20,$L$8:$Q$8)/5) -> 점수 보류 | S20: =IF(OR(ISNUMBER(SEARCH("미통과",J20)),COUNT(K20:P20)<6),"점수 보류",SUMPRODUCT(K20:P20,$L$9:$Q$9)/5) -> 점수 보류 | T20: 하 | U20: 보류 | V20: 공개 자료 부족 | W20: EVD-020
A21: CITY-009 | B21: 강소성 | C21: 苏州(쑤저우) | D21: 昆山(쿤산, 현급시) | E21: 사무 거점만 | F21: 31.38 | G21: 120.98 | H21: 통과 | I21: 확인 필요 | J21: 미통과(1차 명단에 원구 없음) | M21: 3 | N21: 3 | O21: 3 | P21: 4 | Q21: =IF(OR(ISNUMBER(SEARCH("미통과",J21)),COUNT(K21:P21)<6),"점수 보류",SUMPRODUCT(K21:P21,$L$7:$Q$7)/5) -> 점수 보류 | R21: =IF(OR(ISNUMBER(SEARCH("미통과",J21)),COUNT(K21:P21)<6),"점수 보류",SUMPRODUCT(K21:P21,$L$8:$Q$8)/5) -> 점수 보류 | S21: =IF(OR(ISNUMBER(SEARCH("미통과",J21)),COUNT(K21:P21)<6),"점수 보류",SUMPRODUCT(K21:P21,$L$9:$Q$9)/5) -> 점수 보류 | T21: 하 | U21: 창고 거점 제외 | V21: 1차 인정 명단에 쿤산 원구 없음 → 창고는 타 지역 | W21: EVD-020
A22: CITY-010 | B22: 강소성 | C22: 苏州(쑤저우) | D22: 太仓(타이창, 현급시) | E22: 항만 물류 후보 | F22: 31.62 | G22: 121.22 | H22: 통과 | I22: 확인 필요 | J22: 확인 필요(1차 명단 미포함) | M22: 3 | N22: 3 | O22: 3 | P22: 4 | Q22: =IF(OR(ISNUMBER(SEARCH("미통과",J22)),COUNT(K22:P22)<6),"점수 보류",SUMPRODUCT(K22:P22,$L$7:$Q$7)/5) -> 점수 보류 | R22: =IF(OR(ISNUMBER(SEARCH("미통과",J22)),COUNT(K22:P22)<6),"점수 보류",SUMPRODUCT(K22:P22,$L$8:$Q$8)/5) -> 점수 보류 | S22: =IF(OR(ISNUMBER(SEARCH("미통과",J22)),COUNT(K22:P22)<6),"점수 보류",SUMPRODUCT(K22:P22,$L$9:$Q$9)/5) -> 점수 보류 | T22: 하 | U22: 기관 확인 후 결정 | V22: 항만 위험물 범위·2차 명단 확인 필요 | W22: EVD-020
A23: CITY-101 | B23: 상하이시(직할시) | C23: 上海 | D23: 浦东 (外高桥·自贸区) | E23: 법인·수입항·보세 물류 | F23: 31.36 | G23: 121.6 | H23: 통과 | I23: 통과(시 규정·자유무역구 15영업일 사례) | J23: 조건부(化学工业区·항만 창고) | K23: 4 | L23: 3 | M23: 4 | N23: 3 | O23: 2 | P23: 5 | Q23: =IF(OR(ISNUMBER(SEARCH("미통과",J23)),COUNT(K23:P23)<6),"점수 보류",SUMPRODUCT(K23:P23,$L$7:$Q$7)/5) -> 68 | R23: =IF(OR(ISNUMBER(SEARCH("미통과",J23)),COUNT(K23:P23)<6),"점수 보류",SUMPRODUCT(K23:P23,$L$8:$Q$8)/5) -> 71 | S23: =IF(OR(ISNUMBER(SEARCH("미통과",J23)),COUNT(K23:P23)<6),"점수 보류",SUMPRODUCT(K23:P23,$L$9:$Q$9)/5) -> 62 | T23: 중 | U23: 인근 대안 1 · 조건부 | V23: 수입항·보세 물류 강점, 비용 높음 | W23: SRC-031, SRC-032, EVD-016
A24: CITY-102 | B24: 저장성 | C24: 嘉兴(자싱) | D24: 平湖·嘉兴港区 | E24: 창고 거점 대안 | F24: 30.62 | G24: 121.1 | H24: 통과 | I24: 확인 필요 | J24: 조건부(嘉兴 화공원구) | L24: 3 | M24: 3 | N24: 3 | O24: 4 | P24: 3 | Q24: =IF(OR(ISNUMBER(SEARCH("미통과",J24)),COUNT(K24:P24)<6),"점수 보류",SUMPRODUCT(K24:P24,$L$7:$Q$7)/5) -> 점수 보류 | R24: =IF(OR(ISNUMBER(SEARCH("미통과",J24)),COUNT(K24:P24)<6),"점수 보류",SUMPRODUCT(K24:P24,$L$8:$Q$8)/5) -> 점수 보류 | S24: =IF(OR(ISNUMBER(SEARCH("미통과",J24)),COUNT(K24:P24)<6),"점수 보류",SUMPRODUCT(K24:P24,$L$9:$Q$9)/5) -> 점수 보류 | T24: 하 | U24: 보류 | V24: 강소성 창고 미확보 시 대안 | W24: SRC-033
A25: CITY-103 | B25: 저장성 | C25: 宁波(닝보) | D25: 镇海 (宁波石化经开区) | E25: 항만·원구 | F25: 29.98 | G25: 121.66 | H25: 통과 | I25: 확인 필요 | J25: 조건부 | L25: 3 | M25: 3 | N25: 1 | O25: 3 | P25: 3 | Q25: =IF(OR(ISNUMBER(SEARCH("미통과",J25)),COUNT(K25:P25)<6),"점수 보류",SUMPRODUCT(K25:P25,$L$7:$Q$7)/5) -> 점수 보류 | R25: =IF(OR(ISNUMBER(SEARCH("미통과",J25)),COUNT(K25:P25)<6),"점수 보류",SUMPRODUCT(K25:P25,$L$8:$Q$8)/5) -> 점수 보류 | S25: =IF(OR(ISNUMBER(SEARCH("미통과",J25)),COUNT(K25:P25)<6),"점수 보류",SUMPRODUCT(K25:P25,$L$9:$Q$9)/5) -> 점수 보류 | T25: 하 | U25: 제외(거리) | V25: 고객 거리 불리 | W25: SRC-033
A26: CITY-104 | B26: 안후이성 | C26: 合肥(허페이) | D26: 经开区 | E26: CXMT 대응 법인·영업 | F26: 31.75 | G26: 117.24 | H26: 통과 | I26: 확인 필요 | J26: 확인 필요(허페이 원구 미확인) | K26: 3 | M26: 3 | N26: 4 | O26: 4 | P26: 4 | Q26: =IF(OR(ISNUMBER(SEARCH("미통과",J26)),COUNT(K26:P26)<6),"점수 보류",SUMPRODUCT(K26:P26,$L$7:$Q$7)/5) -> 점수 보류 | R26: =IF(OR(ISNUMBER(SEARCH("미통과",J26)),COUNT(K26:P26)<6),"점수 보류",SUMPRODUCT(K26:P26,$L$8:$Q$8)/5) -> 점수 보류 | S26: =IF(OR(ISNUMBER(SEARCH("미통과",J26)),COUNT(K26:P26)<6),"점수 보류",SUMPRODUCT(K26:P26,$L$9:$Q$9)/5) -> 점수 보류 | T26: 하 | U26: 인근 대안 2 · 기관 확인 후 결정 | V26: CXMT 근접. 창고 후보 공개 근거 부족 | W26: EVD-029, SRC-034
A27: CITY-105 | B27: 안후이성 | C27: 滁州(추저우) | D27: - | E27: 창고 거점 대안 | F27: 32.3 | G27: 118.32 | H27: 통과 | I27: 확인 필요 | J27: 확인 필요 | M27: 3 | N27: 3 | O27: 4 | P27: 3 | Q27: =IF(OR(ISNUMBER(SEARCH("미통과",J27)),COUNT(K27:P27)<6),"점수 보류",SUMPRODUCT(K27:P27,$L$7:$Q$7)/5) -> 점수 보류 | R27: =IF(OR(ISNUMBER(SEARCH("미통과",J27)),COUNT(K27:P27)<6),"점수 보류",SUMPRODUCT(K27:P27,$L$8:$Q$8)/5) -> 점수 보류 | S27: =IF(OR(ISNUMBER(SEARCH("미통과",J27)),COUNT(K27:P27)<6),"점수 보류",SUMPRODUCT(K27:P27,$L$9:$Q$9)/5) -> 점수 보류 | T27: 하 | U27: 보류 | V27: 난징 인접, 자료 부족 | W27: SRC-034
A28: CITY-106 | B28: 안후이성 | C28: 芜湖·马鞍山 | D28: - | E28: 창고 거점 대안 | F28: 31.5 | G28: 118.47 | H28: 통과 | I28: 확인 필요 | J28: 확인 필요 | M28: 3 | N28: 3 | O28: 4 | P28: 3 | Q28: =IF(OR(ISNUMBER(SEARCH("미통과",J28)),COUNT(K28:P28)<6),"점수 보류",SUMPRODUCT(K28:P28,$L$7:$Q$7)/5) -> 점수 보류 | R28: =IF(OR(ISNUMBER(SEARCH("미통과",J28)),COUNT(K28:P28)<6),"점수 보류",SUMPRODUCT(K28:P28,$L$8:$Q$8)/5) -> 점수 보류 | S28: =IF(OR(ISNUMBER(SEARCH("미통과",J28)),COUNT(K28:P28)<6),"점수 보류",SUMPRODUCT(K28:P28,$L$9:$Q$9)/5) -> 점수 보류 | T28: 하 | U28: 보류 | V28: 자료 부족 | W28: SRC-034

Sheet 09_SitesWarehouses
A1: 09_SitesWarehouses | 단지·창고 후보
A2: 공개 근거로 확인된 것은 '인정 화공원구' 지위까지. 위험품 창고·품목·특수 물성 수용은 모두 문의 예정
A3: 조사 기준일 2026-10-06 · 단위·상태는 각 열 머리글 참조
A5: 시설 ID | B5: 도시 ID | C5: 단지·창고 정식 명칭 | D5: 주소 | E5: 운영사 | F5: 시설 종류 | G5: 공식 인정·허가 | H5: 취급 가능 품목 | I5: 특수 물성 수용 | J5: 외자·무역법인 입주 | K5: 임차 조건 | L5: 공개 연락처 | M5: 문의 상태 | N5: 견적 필요 | O5: 근거 ID
A6: SITE-001 | B6: CITY-001 | C6: 江阴临港化工园区 (무석 관할 강음시) | D6: 공개 주소 미수집 | E6: 원구 관리위원회 | F6: 인정 화공원구 | G6: 강소성 1차 인정 | H6: 확인 필요 | I6: 확인 필요 | J6: 확인 필요 | K6: 확인 필요 | L6: 공식 사이트 확인 예정 | M6: 문의 예정 | N6: 필요 | O6: EVD-020
A7: SITE-002 | B7: CITY-001 | C7: 锡山经济技术开发区新材料产业园 | D7: 공개 주소 미수집 | E7: 원구 관리 | F7: 인정 화공원구 | G7: 강소성 1차 인정 | H7: 확인 필요 | I7: 확인 필요 | J7: 확인 필요 | K7: 확인 필요 | L7: - | M7: 문의 예정 | N7: 필요 | O7: EVD-020
A8: SITE-003 | B8: CITY-001 | C8: 宜兴市新材料产业园 | D8: 공개 주소 미수집 | E8: 원구 관리 | F8: 인정 화공원구 | G8: 강소성 1차 인정 | H8: 확인 필요 | I8: 확인 필요 | J8: 확인 필요 | K8: 확인 필요 | L8: - | M8: 문의 예정 | N8: 필요 | O8: EVD-020
A9: SITE-004 | B9: CITY-001 | C9: 무석 신오구 사무 공간 (무저장 경영 장소) | D9: - | E9: 임대인 | F9: 일반 업무용 건물 | G9: - | H9: 보관 금지(무저장) | I9: - | J9: 가능(일반) | K9: 견적 필요 | L9: - | M9: 문의 예정 | N9: 필요 | O9: EVD-015
A10: SITE-005 | B10: CITY-002 | C10: 江苏扬子江国际化学工业园 / 张家港保税区 위험품 물류 | D10: 공개 주소 미수집 | E10: 원구·물류사 | F10: 인정 화공원구·보세구 | G10: 강소성 1차 인정 | H10: 위험화학품 부두·보세 위험품 창고(보도) | I10: 확인 필요(4.2·4.3류) | J10: 확인 필요 | K10: 견적 필요 | L10: - | M10: 문의 예정 | N10: 필요 | O10: EVD-021
A11: SITE-006 | B11: CITY-002 | C11: 江苏高科技氟化学工业园(常熟新材料产业园) | D11: 공개 주소 미수집 | E11: 원구 관리 | F11: 인정 화공원구 | G11: 강소성 1차 인정 | H11: 불소화학 중심 | I11: 확인 필요 | J11: 확인 필요 | K11: 확인 필요 | L11: - | M11: 문의 예정 | N11: 필요 | O11: EVD-020
A12: SITE-007 | B12: CITY-003 | C12: 常州滨江经济开发区新材料产业园 | D12: 공개 주소 미수집 | E12: 원구 관리 | F12: 인정 화공원구 | G12: 강소성 1차 인정 | H12: 확인 필요 | I12: 확인 필요 | J12: 확인 필요 | K12: 확인 필요 | L12: - | M12: 문의 예정 | N12: 필요 | O12: EVD-020
A13: SITE-008 | B13: CITY-004 | C13: 镇江新区新材料产业园 | D13: 공개 주소 미수집 | E13: 원구 관리 | F13: 인정 화공원구 | G13: 강소성 1차 인정 | H13: 확인 필요 | I13: 확인 필요 | J13: 확인 필요 | K13: 확인 필요 | L13: - | M13: 문의 예정 | N13: 필요 | O13: EVD-020
A14: SITE-009 | B14: CITY-006 | C14: 南京江北新材料科技园 | D14: 공개 주소 미수집 | E14: 원구 관리 | F14: 인정 화공원구 | G14: 강소성 1차 인정 | H14: 확인 필요 | I14: 확인 필요 | J14: 확인 필요 | K14: 확인 필요 | L14: - | M14: 문의 예정 | N14: 필요 | O14: EVD-020
A15: SITE-010 | B15: CITY-005 | C15: 南通经济技术开发区化工园区(南区)·如东洋口·如皋港 | D15: 공개 주소 미수집 | E15: 원구 관리 | F15: 인정 화공원구 | G15: 강소성 1차 인정 | H15: 확인 필요 | I15: 확인 필요 | J15: 확인 필요 | K15: 확인 필요 | L15: - | M15: 문의 예정 | N15: 필요 | O15: EVD-020
A16: SITE-011 | B16: CITY-101 | C16: 上海化学工业区 / 외고교 항만·보세 물류 | D16: 공개 주소 미수집 | E16: 원구·물류사 | F16: 화공원구·보세구 | G16: 상하이 시 지정(확인 필요) | H16: 확인 필요 | I16: 확인 필요 | J16: 확인 필요 | K16: 견적 필요 | L16: - | M16: 문의 예정 | N16: 필요 | O16: SRC-031, SRC-032
... A18: SITE-013 | B18: CITY-104 | C18: 허페이 위험화학품 창고 후보 (미특정) | D18: - | E18: - | F18: 미특정 | G18: 정보 없음 | H18: 정보 없음 | I18: 정보 없음 | J18: 정보 없음 | K18: 정보 없음 | L18: - | M18: 문의 예정 | N18: 필요 | O18: 정보 없음

Sheet 10_OperatingModels
A1: 10_OperatingModels | 운영 구조 A~G
A2: 법적 가능성은 근거 기반 판단(기관 확인 전). 비용·기간은 상대 비교
A3: 조사 기준일 2026-10-06 · 단위·상태는 각 열 머리글 참조
A5: 구조 ID | B5: 구조 | C5: 등록 주체 | D5: 수입자 | E5: 판매자 | F5: 창고 운영자 | G5: 필요 허가 | H5: 법적 가능성 | I5: 선행 조건 | J5: IP·자료 | K5: 책임 | L5: 투자·운영비 | M5: 기간 | N5: 고객 승인 | O5: 장점 | P5: 단점 | Q5: 근거 ID
A6: A | B6: MP 중국법인 활용 | C6: MP(개정안 시) / TC+대리인(현행) | D6: MP | E6: MP | F6: MP 또는 3PL | G6: MP 명의 경영허가·위험화학품 등록 | H6: 가능(MP 허가 보유 시) | I6: MP 허가·사업범위 확인 | J6: MP에 자료 노출 | K6: MP 1차 책임 | L6: MP 보유 시 최소 | M6: MP 보유 시 최단 | N6: 공급자=MP 변경 협의 | O6: 기존 법인·인력 활용 | P6: TC 통제권 약함, 등록증이 MP 명의 | Q6: EVD-002
A7: B | B7: TC 법인 + 무저장 경영 + 허가 외부 창고 | C7: TC 법인 | D7: TC 법인 | E7: TC 법인 | F7: 허가 3PL | G7: TC: 무저장 경영허가·위험화학품 등록 / 3PL: 창고 경영허가 | H7: 가능(근거 기반, 무석 세칙에 무저장 유형) | I7: 3PL의 품목·물성 수용 | J7: TC 법인 내부 통제 | K7: TC 수입·판매 책임, 보관 책임은 계약 분담 | L7: 낮음 | M7: 3~6개월(가정) | N7: 공급자 변경 필요 | O7: 최소 투자로 등록·수입 주체 확보 | P7: 3PL 품목 범위에 종속 | Q7: EVD-014, EVD-015
A8: C | B8: TC 법인 + 임차 전용 창고 | C8: TC 법인 | D8: TC 법인 | E8: TC 법인 | F8: TC(임차) | G8: 임차저장 경영허가·안전협의 | H8: 가능성 있음(무석 세칙에 임차저장 유형) | I8: 화공원구 내 허가 창고 임차 | J8: TC 통제 강화 | K8: TC 저장 책임 증가 | L8: 중간 | M8: 6~9개월(가정) | N8: 동일 | O8: 재고·품질 직접 관리 | P8: 인력·안전 요건 증가 | Q8: EVD-013, EVD-014
A9: D | B9: TC 법인 + 자체 창고·시설 | C9: TC 법인 | D9: TC 법인 | E9: TC 법인 | F9: TC | G9: 저장 경영허가·건설 안전·환경·소방 | H9: 가능(원구 입주 승인 전제) | I9: 원구 입주·토지·건설 | J9: 최대 통제 | K9: 전 책임 | L9: 높음 | M9: 12~24개월(가정) | N9: 동일 | O9: 장기 확장(충진 등) | P9: 초기 투자·기간 큼 | Q9: EVD-013
A10: E | B10: 관리 거점과 창고 거점 분리 | C10: TC 법인 | D10: TC 법인 | E10: TC 법인 | F10: 타 도시·타 성 3PL | G10: 법인 소재지 경영허가 + 창고 소재지 운영사 허가 | H10: B안의 변형으로 가능성 높음(기관 확인) | I10: 허가 관할·운송 경로 | J10: B와 동일 | K10: 관할 분리 관리 | L10: 낮음~중간 | M10: B와 유사 | N10: 동일 | O10: 도시 선택 자유도 | P10: 관할 확인 필요 | Q10: 기관 확인 필요
A11: F | B11: 충진·소분 등 제조 포함 | C11: TC 법인 | D11: TC 법인 | E11: TC 법인 | F11: TC | G11: 안전생산허가 또는 분장·충진 경영 + 건설·환경 | H11: 현 단계 불필요 | I11: 제조 필요성 확정 | J11: - | K11: 생산 책임 | L11: 매우 높음 | M11: 24개월+(가정) | N11: 재승인 | O11: 장기 원가·대응력 | P11: 지금은 과잉 투자 | Q11: EVD-011, EVD-033
A12: G | B12: 법인 설립 전 대리인·적격 수입자 활용 | C12: TC 본사+대리인(현행) / 수입자(개정안) | D12: 적격 수입자(고객·유통사) | E12: 적격 수입자 | F12: 수입자 창고 | G12: 수입자 보유 허가 | H12: 현행 규정상 가능, 개정 시 수입자 명의 | I12: 대리·수입 계약 | J12: 대리인·수입자 노출 | K12: 계약 분담 | L12: 낮음 | M12: 가장 빠름 | N12: 기존 구조 유지 가능 | O12: 연말 대응 수단 | P12: 등록증 명의·이관 문제 | Q12: EVD-001, EVD-002, EVD-005

Sheet 11_MPComparison
A1: 11_MPComparison | MP 활용 vs TC 독자 법인
A2: MP 핵심 정보 미제공 → 시나리오 1(MP 허가 보유)·2(MP 신규 취득)로 비교
A3: 조사 기준일 2026-10-06 · 단위·상태는 각 열 머리글 참조
A5: 비교 항목 | B5: MP 현황 | C5: TC 신규 법인 조건 | D5: 시나리오1: MP 허가 보유 | E5: 시나리오2: MP 신규 취득 | F5: 수수료·책임 | G5: 비용·기간 차이 | H5: 데이터 상태 | I5: 내부 확인 질문
A6: 법인 실체 | B6: 정식 명칭·소재지 미제공 | C6: 신규 설립(등기 수주) | D6: 즉시 활용 | E6: 즉시 활용(법인은 존재) | F6: - | G6: MP 우위 | H6: 정보 없음 | I6: MP 정식 법인명·주소·지분
A7: 사업범위 | B7: 미제공 | C7: 설립 시 화학품 도매 포함 | D7: 범위 내면 즉시 | E7: 변경 등기 필요 | F7: - | G7: 유사 | H7: 정보 없음 | I7: 营业执照 사업범위
A8: 위험화학품 경영허가 | B8: 미보유 언급(미확인) | C8: 신규 취득 | D8: 즉시 사용 | E8: 신규 취득(TC와 동일) | F8: - | G8: S1: MP 우위 / S2: 차이 없음 | H8: 내부 제공 | I8: 허가증 사본·품목·저장 방식
A9: 수입기업 위험화학품 등록 | B9: 미제공 | C9: 신규 | D9: 품목 추가 | E9: 신규 | F9: - | G9: S2: 차이 없음 | H9: 정보 없음 | I9: 등록 실적
A10: 신규화학물질 등록 주체 | B10: 미제공 | C10: TC 법인 명의 | D10: MP 명의 | E10: MP 명의 | F10: MP에 자료·권리 귀속 위험 | G10: TC 우위(통제권) | H10: 정보 없음 | I10: 등록 수행 의향·자료 접근 범위
A11: 창고 | B11: 미제공 | C11: 3PL 계약 | D11: MP 창고 활용 가능 | E11: 3PL 계약(동일) | F11: 보관 책임 계약 | G11: S1: MP 우위 | H11: 정보 없음 | I11: 창고 보유·품목
A12: 인력 | B12: 미제공 | C12: 4~5명 채용·파견 | D12: 겸직 가능 | E12: 추가 채용 | F12: 인건비 배분 | G12: S1: MP 우위 | H12: 정보 없음 | I12: TC 업무 담당 가능 인원
A13: 의사결정·우선순위 | B13: - | C13: TC 직접 | D13: MP 내부 우선순위에 종속 | E13: 동일 | F13: 서비스 수준 계약 필요 | G13: TC 우위 | H13: 분석 가정 | I13: SLA 수용 의향
A14: 이전가격·관계자 거래 | B14: - | C14: TC 본사–TC 법인 | D14: TC–MP 서비스 대가·이전가격 | E14: 동일 | F14: 세무 위험 | G14: TC 단순 | H14: 분석 가정 | I14: 그룹 이전가격 정책
A15: 계약 종료 시 | B15: - | C15: 해당 없음 | D15: 등록증·재고·고객 이관 문제 | E15: 동일 | F15: 등록증 변경=재신청 가능성 | G15: TC 우위 | H15: 전문가 자료 | I15: -

Sheet 12_LogisticsStaff
A1: 12_LogisticsStaff | 거리(직선)·인력
A2: 직선거리 = 좌표(도시·구 중심, 대략) 기준 수식. 도로거리·운송 리드타임은 운송사 확인 필요
A3: 조사 기준일 2026-10-06 · 단위·상태는 각 열 머리글 참조
A5: 도시 ID | B5: 도시 | C5: 위도 | D5: 경도 | E5: 직선거리 CXMT(km) | F5: 직선거리 SK하이닉스 우시(km) | G5: 직선거리 YMTC(km) | H5: 도로거리·시간 | I5: 위험물 운송 리드타임
A6: CITY-001 | B6: 无锡(무석) 新吴区(신오구) | C6: =INDEX('08_CityComparison'!$F$13:$F$28,MATCH(A6,'08_CityComparison'!$A$13:$A$28,0)) -> 31.55 | D6: =INDEX('08_CityComparison'!$G$13:$G$28,MATCH(A6,'08_CityComparison'!$A$13:$A$28,0)) -> 120.37 | E6: =ROUND(6371*ACOS(MIN(1,SIN(RADIANS(C6))*SIN(RADIANS(31.75))+COS(RADIANS(C6))*COS(RADIANS(31.75))*COS(RADIANS(117.25-D6)))),0) -> 296 | F6: =ROUND(6371*ACOS(MIN(1,SIN(RADIANS(C6))*SIN(RADIANS(31.55))+COS(RADIANS(C6))*COS(RADIANS(31.55))*COS(RADIANS(120.4-D6)))),0) -> 3 | G6: =ROUND(6371*ACOS(MIN(1,SIN(RADIANS(C6))*SIN(RADIANS(30.45))+COS(RADIANS(C6))*COS(RADIANS(30.45))*COS(RADIANS(114.55-D6)))),0) -> 568 | H6: 확인 필요 | I6: 확인 필요
A7: CITY-002 | B7: 苏州(쑤저우) 工业园区(SIP) + 张家港(장자강, 현급시) | C7: =INDEX('08_CityComparison'!$F$13:$F$28,MATCH(A7,'08_CityComparison'!$A$13:$A$28,0)) -> 31.32 | D7: =INDEX('08_CityComparison'!$G$13:$G$28,MATCH(A7,'08_CityComparison'!$A$13:$A$28,0)) -> 120.72 | E7: =ROUND(6371*ACOS(MIN(1,SIN(RADIANS(C7))*SIN(RADIANS(31.75))+COS(RADIANS(C7))*COS(RADIANS(31.75))*COS(RADIANS(117.25-D7)))),0) -> 332 | F7: =ROUND(6371*ACOS(MIN(1,SIN(RADIANS(C7))*SIN(RADIANS(31.55))+COS(RADIANS(C7))*COS(RADIANS(31.55))*COS(RADIANS(120.4-D7)))),0) -> 40 | G7: =ROUND(6371*ACOS(MIN(1,SIN(RADIANS(C7))*SIN(RADIANS(30.45))+COS(RADIANS(C7))*COS(RADIANS(30.45))*COS(RADIANS(114.55-D7)))),0) -> 597 | H7: 확인 필요 | I7: 확인 필요
A8: CITY-003 | B8: 常州(창저우) 新北区 滨江경개구 | C8: =INDEX('08_CityComparison'!$F$13:$F$28,MATCH(A8,'08_CityComparison'!$A$13:$A$28,0)) -> 31.98 | D8: =INDEX('08_CityComparison'!$G$13:$G$28,MATCH(A8,'08_CityComparison'!$A$13:$A$28,0)) -> 119.9 | E8: =ROUND(6371*ACOS(MIN(1,SIN(RADIANS(C8))*SIN(RADIANS(31.75))+COS(RADIANS(C8))*COS(RADIANS(31.75))*COS(RADIANS(117.25-D8)))),0) -> 252 | F8: =ROUND(6371*ACOS(MIN(1,SIN(RADIANS(C8))*SIN(RADIANS(31.55))+COS(RADIANS(C8))*COS(RADIANS(31.55))*COS(RADIANS(120.4-D8)))),0) -> 67 | G8: =ROUND(6371*ACOS(MIN(1,SIN(RADIANS(C8))*SIN(RADIANS(30.45))+COS(RADIANS(C8))*COS(RADIANS(30.45))*COS(RADIANS(114.55-D8)))),0) -> 536 | H8: 확인 필요 | I8: 확인 필요
A9: CITY-004 | B9: 镇江(전장) 镇江新区 | C9: =INDEX('08_CityComparison'!$F$13:$F$28,MATCH(A9,'08_CityComparison'!$A$13:$A$28,0)) -> 32.18 | D9: =INDEX('08_CityComparison'!$G$13:$G$28,MATCH(A9,'08_CityComparison'!$A$13:$A$28,0)) -> 119.68 | E9: =ROUND(6371*ACOS(MIN(1,SIN(RADIANS(C9))*SIN(RADIANS(31.75))+COS(RADIANS(C9))*COS(RADIANS(31.75))*COS(RADIANS(117.25-D9)))),0) -> 234 | F9: =ROUND(6371*ACOS(MIN(1,SIN(RADIANS(C9))*SIN(RADIANS(31.55))+COS(RADIANS(C9))*COS(RADIANS(31.55))*COS(RADIANS(120.4-D9)))),0) -> 98 | G9: =ROUND(6371*ACOS(MIN(1,SIN(RADIANS(C9))*SIN(RADIANS(30.45))+COS(RADIANS(C9))*COS(RADIANS(30.45))*COS(RADIANS(114.55-D9)))),0) -> 524 | H9: 확인 필요 | I9: 확인 필요
A10: CITY-005 | B10: 南通(난퉁) 경개구·如东·如皋 | C10: =INDEX('08_CityComparison'!$F$13:$F$28,MATCH(A10,'08_CityComparison'!$A$13:$A$28,0)) -> 31.95 | D10: =INDEX('08_CityComparison'!$G$13:$G$28,MATCH(A10,'08_CityComparison'!$A$13:$A$28,0)) -> 120.95 | E10: =ROUND(6371*ACOS(MIN(1,SIN(RADIANS(C10))*SIN(RADIANS(31.75))+COS(RADIANS(C10))*COS(RADIANS(31.75))*COS(RADIANS(117.25-D10)))),0) -> 350 | F10: =ROUND(6371*ACOS(MIN(1,SIN(RADIANS(C10))*SIN(RADIANS(31.55))+COS(RADIANS(C10))*COS(RADIANS(31.55))*COS(RADIANS(120.4-D10)))),0) -> 68 | G10: =ROUND(6371*ACOS(MIN(1,SIN(RADIANS(C10))*SIN(RADIANS(30.45))+COS(RADIANS(C10))*COS(RADIANS(30.45))*COS(RADIANS(114.55-D10)))),0) -> 631 | H10: 확인 필요 | I10: 확인 필요
A11: CITY-006 | B11: 南京(난징) 江北新区 (江北新材料科技园) | C11: =INDEX('08_CityComparison'!$F$13:$F$28,MATCH(A11,'08_CityComparison'!$A$13:$A$28,0)) -> 32.26 | D11: =INDEX('08_CityComparison'!$G$13:$G$28,MATCH(A11,'08_CityComparison'!$A$13:$A$28,0)) -> 118.85 | E11: =ROUND(6371*ACOS(MIN(1,SIN(RADIANS(C11))*SIN(RADIANS(31.75))+COS(RADIANS(C11))*COS(RADIANS(31.75))*COS(RADIANS(117.25-D11)))),0) -> 161 | F11: =ROUND(6371*ACOS(MIN(1,SIN(RADIANS(C11))*SIN(RADIANS(31.55))+COS(RADIANS(C11))*COS(RADIANS(31.55))*COS(RADIANS(120.4-D11)))),0) -> 166 | G11: =ROUND(6371*ACOS(MIN(1,SIN(RADIANS(C11))*SIN(RADIANS(30.45))+COS(RADIANS(C11))*COS(RADIANS(30.45))*COS(RADIANS(114.55-D11)))),0) -> 455 | H11: 확인 필요 | I11: 확인 필요
A12: CITY-007 | B12: 扬州(양저우) 仪征 (扬州化学工业园区) | C12: =INDEX('08_CityComparison'!$F$13:$F$28,MATCH(A12,'08_CityComparison'!$A$13:$A$28,0)) -> 32.27 | D12: =INDEX('08_CityComparison'!$G$13:$G$28,MATCH(A12,'08_CityComparison'!$A$13:$A$28,0)) -> 119.18 | E12: =ROUND(6371*ACOS(MIN(1,SIN(RADIANS(C12))*SIN(RADIANS(31.75))+COS(RADIANS(C12))*COS(RADIANS(31.75))*COS(RADIANS(117.25-D12)))),0) -> 191 | F12: =ROUND(6371*ACOS(MIN(1,SIN(RADIANS(C12))*SIN(RADIANS(31.55))+COS(RADIANS(C12))*COS(RADIANS(31.55))*COS(RADIANS(120.4-D12)))),0) -> 140 | G12: =ROUND(6371*ACOS(MIN(1,SIN(RADIANS(C12))*SIN(RADIANS(30.45))+COS(RADIANS(C12))*COS(RADIANS(30.45))*COS(RADIANS(114.55-D12)))),0) -> 484 | H12: 확인 필요 | I12: 확인 필요
A13: CITY-008 | B13: 泰州(타이저우) 泰兴·滨江 | C13: =INDEX('08_CityComparison'!$F$13:$F$28,MATCH(A13,'08_CityComparison'!$A$13:$A$28,0)) -> 32.17 | D13: =INDEX('08_CityComparison'!$G$13:$G$28,MATCH(A13,'08_CityComparison'!$A$13:$A$28,0)) -> 120.02 | E13: =ROUND(6371*ACOS(MIN(1,SIN(RADIANS(C13))*SIN(RADIANS(31.75))+COS(RADIANS(C13))*COS(RADIANS(31.75))*COS(RADIANS(117.25-D13)))),0) -> 265 | F13: =ROUND(6371*ACOS(MIN(1,SIN(RADIANS(C13))*SIN(RADIANS(31.55))+COS(RADIANS(C13))*COS(RADIANS(31.55))*COS(RADIANS(120.4-D13)))),0) -> 78 | G13: =ROUND(6371*ACOS(MIN(1,SIN(RADIANS(C13))*SIN(RADIANS(30.45))+COS(RADIANS(C13))*COS(RADIANS(30.45))*COS(RADIANS(114.55-D13)))),0) -> 554 | H13: 확인 필요 | I13: 확인 필요
A14: CITY-009 | B14: 苏州(쑤저우) 昆山(쿤산, 현급시) | C14: =INDEX('08_CityComparison'!$F$13:$F$28,MATCH(A14,'08_CityComparison'!$A$13:$A$28,0)) -> 31.38 | D14: =INDEX('08_CityComparison'!$G$13:$G$28,MATCH(A14,'08_CityComparison'!$A$13:$A$28,0)) -> 120.98 | E14: =ROUND(6371*ACOS(MIN(1,SIN(RADIANS(C14))*SIN(RADIANS(31.75))+COS(RADIANS(C14))*COS(RADIANS(31.75))*COS(RADIANS(117.25-D14)))),0) -> 356 | F14: =ROUND(6371*ACOS(MIN(1,SIN(RADIANS(C14))*SIN(RADIANS(31.55))+COS(RADIANS(C14))*COS(RADIANS(31.55))*COS(RADIANS(120.4-D14)))),0) -> 58 | G14: =ROUND(6371*ACOS(MIN(1,SIN(RADIANS(C14))*SIN(RADIANS(30.45))+COS(RADIANS(C14))*COS(RADIANS(30.45))*COS(RADIANS(114.55-D14)))),0) -> 622 | H14: 확인 필요 | I14: 확인 필요
A15: CITY-010 | B15: 苏州(쑤저우) 太仓(타이창, 현급시) | C15: =INDEX('08_CityComparison'!$F$13:$F$28,MATCH(A15,'08_CityComparison'!$A$13:$A$28,0)) -> 31.62 | D15: =INDEX('08_CityComparison'!$G$13:$G$28,MATCH(A15,'08_CityComparison'!$A$13:$A$28,0)) -> 121.22 | E15: =ROUND(6371*ACOS(MIN(1,SIN(RADIANS(C15))*SIN(RADIANS(31.75))+COS(RADIANS(C15))*COS(RADIANS(31.75))*COS(RADIANS(117.25-D15)))),0) -> 376 | F15: =ROUND(6371*ACOS(MIN(1,SIN(RADIANS(C15))*SIN(RADIANS(31.55))+COS(RADIANS(C15))*COS(RADIANS(31.55))*COS(RADIANS(120.4-D15)))),0) -> 78 | G15: =ROUND(6371*ACOS(MIN(1,SIN(RADIANS(C15))*SIN(RADIANS(30.45))+COS(RADIANS(C15))*COS(RADIANS(30.45))*COS(RADIANS(114.55-D15)))),0) -> 649 | H15: 확인 필요 | I15: 확인 필요
A16: CITY-101 | B16: 上海 浦东 (外高桥·自贸区) | C16: =INDEX('08_CityComparison'!$F$13:$F$28,MATCH(A16,'08_CityComparison'!$A$13:$A$28,0)) -> 31.36 | D16: =INDEX('08_CityComparison'!$G$13:$G$28,MATCH(A16,'08_CityComparison'!$A$13:$A$28,0)) -> 121.6 | E16: =ROUND(6371*ACOS(MIN(1,SIN(RADIANS(C16))*SIN(RADIANS(31.75))+COS(RADIANS(C16))*COS(RADIANS(31.75))*COS(RADIANS(117.25-D16)))),0) -> 414 | F16: =ROUND(6371*ACOS(MIN(1,SIN(RADIANS(C16))*SIN(RADIANS(31.55))+COS(RADIANS(C16))*COS(RADIANS(31.55))*COS(RADIANS(120.4-D16)))),0) -> 116 | G16: =ROUND(6371*ACOS(MIN(1,SIN(RADIANS(C16))*SIN(RADIANS(30.45))+COS(RADIANS(C16))*COS(RADIANS(30.45))*COS(RADIANS(114.55-D16)))),0) -> 680 | H16: 확인 필요 | I16: 확인 필요
A17: CITY-102 | B17: 嘉兴(자싱) 平湖·嘉兴港区 | C17: =INDEX('08_CityComparison'!$F$13:$F$28,MATCH(A17,'08_CityComparison'!$A$13:$A$28,0)) -> 30.62 | D17: =INDEX('08_CityComparison'!$G$13:$G$28,MATCH(A17,'08_CityComparison'!$A$13:$A$28,0)) -> 121.1 | E17: =ROUND(6371*ACOS(MIN(1,SIN(RADIANS(C17))*SIN(RADIANS(31.75))+COS(RADIANS(C17))*COS(RADIANS(31.75))*COS(RADIANS(117.25-D17)))),0) -> 387 | F17: =ROUND(6371*ACOS(MIN(1,SIN(RADIANS(C17))*SIN(RADIANS(31.55))+COS(RADIANS(C17))*COS(RADIANS(31.55))*COS(RADIANS(120.4-D17)))),0) -> 123 | G17: =ROUND(6371*ACOS(MIN(1,SIN(RADIANS(C17))*SIN(RADIANS(30.45))+COS(RADIANS(C17))*COS(RADIANS(30.45))*COS(RADIANS(114.55-D17)))),0) -> 628 | H17: 확인 필요 | I17: 확인 필요
... A21: CITY-106 | B21: 芜湖·马鞍山 - | C21: =INDEX('08_CityComparison'!$F$13:$F$28,MATCH(A21,'08_CityComparison'!$A$13:$A$28,0)) -> 31.5 | D21: =INDEX('08_CityComparison'!$G$13:$G$28,MATCH(A21,'08_CityComparison'!$A$13:$A$28,0)) -> 118.47 | E21: =ROUND(6371*ACOS(MIN(1,SIN(RADIANS(C21))*SIN(RADIANS(31.75))+COS(RADIANS(C21))*COS(RADIANS(31.75))*COS(RADIANS(117.25-D21)))),0) -> 119 | F21: =ROUND(6371*ACOS(MIN(1,SIN(RADIANS(C21))*SIN(RADIANS(31.55))+COS(RADIANS(C21))*COS(RADIANS(31.55))*COS(RADIANS(120.4-D21)))),0) -> 183 | G21: =ROUND(6371*ACOS(MIN(1,SIN(RADIANS(C21))*SIN(RADIANS(30.45))+COS(RADIANS(C21))*COS(RADIANS(30.45))*COS(RADIANS(114.55-D21)))),0) -> 392 | H21: 확인 필요 | I21: 확인 필요
A24: 고객 위치 (공개 주소 기준)
A25: CUST-01 | B25: CXMT (长鑫存储) | C25: 안후이 허페이 경제기술개발구 (등록 주소) | D25: 31.75 | E25: 117.25 | F25: EVD-029 | G25: 공개 주소 기준 · 반입 위치 고객 확인
A26: CUST-02 | B26: SK하이닉스 우시 | C26: 강소 무석 신오구 | D26: 31.55 | E26: 120.4 | F26: EVD-031 | G26: 구 단위 위치 · 반입 위치 고객 확인
A27: CUST-03 | B27: YMTC (长江存储) | C27: 후베이 우한 동호고신구 | D27: 30.45 | E27: 114.55 | F27: EVD-030 | G27: 지도 범위 밖(서쪽)
A29: 인력 역할 (최소안 vs 확대안)
A30: 역할 | B30: 법정·운영 구분 | C30: 자격·교육 | D30: 겸직·외주 | E30: 상주 | F30: 현지/주재원 | G30: 최소안(명) | H30: 확대안(명) | I30: 근거 ID
A31: 법인장·법정대표인(이사 또는 경리) | B31: 법정(법정대표인 1명) | C31: 위험화학품 경영 '주요 책임자' 교육·시험 | D31: 겸직 가능(이사 겸) | E31: 권장 | F31: 주재원(이동선 총감 구상) | G31: 1 | H31: 1 | I31: EVD-023, EVD-012
A32: 전담 안전관리자 | B32: 경영허가 조건(전담) | C32: 안전관리자 교육·시험 합격 | D32: 겸직 불가(전담 요구) | E32: 필요 | F32: 현지 | G32: 1 | H32: 1 | I32: EVD-012
A33: 영업·고객 기술 대응 | B33: 운영 필요 | C33: - | D33: 법인장 일부 겸 | E33: 필요 | F33: 현지/주재원 | G33: 1 | H33: 2 | I33: 분석 가정
A34: 수입·물류·통관·재고 | B34: 운영 필요 | C34: 위험물 운송 지식 | D34: 안전관리자와 분리 권장 | E34: 필요 | F34: 현지 | G34: 0 | H34: 1 | I34: 분석 가정
A35: 재무·세무·회계(경리) | B35: 세무 등록 실무상 필요 | C35: - | D35: 회계 대행 외주 가능 | E35: 부분 | F35: 현지 | G35: 1 | H35: 1 | I35: 분석 가정
A36: 창고 운영·품질 | B36: C·D안에서 필요 | C36: 위험화학품 창고 교육 | D36: B안은 3PL 수행 | E36: C·D안 | F36: 현지 | G36: 0 | H36: 2 | I36: 분석 가정
A37: 합계 | G37: =SUM(G31:G36) -> 4 | H37: =SUM(H31:H36) -> 8
A38: 회의 구상 4명(이동선 총감·신규 채용·최영진·경리)은 전담 안전관리자 1명이 포함될 때 무저장(B안) 최소 운영 가능 — 법정 최소 인원 아님

Sheet 13_FXAssumptions
A1: 13_FXAssumptions | 환율·단가·가정 입력
A2: 파란 칸만 수정. 빈 칸 = 견적 필요(0 아님)
A3: 조사 기준일 2026-10-06 · 단위·상태는 각 열 머리글 참조
A5: 가정 ID | B5: 항목 | C5: 입력값 | D5: 단위 | E5: 통화 | F5: 적용일 | G5: 환율·출처 | H5: 가정 이유 | I5: 적용 구조 | J5: 범위 | K5: 확인 상태 | L5: 변경 영향
A6: ASM-001 | B6: 환율 CNY→KRW | C6: 204 | D6: KRW/CNY | E6: KRW | F6: 2026-09-01 | G6: SRC-026 | H6: 검색 확인 최근값 | I6: 전체 | J6: 195~215 | K6: 언론·기타 | L6: KRW 환산 전체
A7: ASM-002 | B7: 현지 직원 연 기본급 (무석 평균임금 기준) | C7: 147293 | D7: CNY/인·년 | E7: CNY | F7: 2025 | G7: SRC-024 | H7: 직무 시장급여 미확보 → 평균임금 사용 | I7: B·C | J7: - | K7: 언론·기타 | L7: 인건비
A8: ASM-003 | B8: 직무 급여 배수 (평균 대비) | C8: 1.2 | D8: 배 | E8: - | F8: - | G8: 분석 가정 | H8: 전문직(영업·안전) 프리미엄 | I8: B·C | J8: 1.0~1.5 | K8: 분석 가정 | L8: 인건비
A9: ASM-004 | B9: 사업주 사회보험·주택공적금 부담률 | C9: 0.35 | D9: 비율 | E9: - | F9: - | G9: 분석 가정 (강소성 요율 확인 필요) | H9: - | I9: B·C | J9: 0.30~0.40 | K9: 분석 가정 | L9: 인건비
A10: ASM-005 | B10: 현지 채용 인원 (최소안) | C10: 3 | D10: 명 | E10: - | F10: - | G10: 인력표: 안전관리자·영업·경리 | H10: 법인장은 주재원 | I10: B | J10: 3~4 | K10: 분석 가정 | L10: 인건비
A11: ASM-006 | B11: 사무실 면적 | C11: 120 | D11: ㎡ | E11: - | F11: - | G11: 분석 가정 | H11: 4~5명 + 회의실 | I11: B·C | J11: 80~150 | K11: 분석 가정 | L11: 임대료
A12: ASM-007 | B12: 사무실 임대 단가 | D12: CNY/㎡·월 | E12: CNY | F12: - | G12: 견적 필요 (무석 공개 시세 미확보) | H12: - | I12: B·C | J12: - | K12: 기관 확인 필요 | L12: 임대료
A13: ASM-008 | B13: 보증금 개월수 | C13: 3 | D13: 개월 | E13: - | F13: - | G13: 분석 가정 | H13: - | I13: B·C | J13: 2~3 | K13: 분석 가정 | L13: 보증금(회수 가능)
A14: ASM-009 | B14: 현지 재고 일수 (민감도) | C14: 30 | D14: 일 | E14: - | F14: - | G14: 분석 가정 (고객 요구 미제공) | H14: 1·2·3개월 비교 | I14: B·C | J14: 30/60/90 | K14: 분석 가정 | L14: 운전자본
A15: ASM-010 | B15: 월 판매액 (중국 공급) | D15: CNY/월 | E15: CNY | F15: - | G15: 미제공 | H15: 매출 계획 창작 금지 | I15: - | J15: - | K15: 정보 없음 | L15: 운전자본·손익분기
A16: ASM-011 | B16: 등록자본 = 첫해 고정비 × 배수 | C16: 1.5 | D16: 배 | E16: - | F16: - | G16: 분석 가정 | H16: 운영 18개월분 수준 | I16: B | J16: 1.0~2.0 | K16: 분석 가정 | L16: 등록자본

Sheet 14_CostsRaw
A1: 14_CostsRaw | 비용 원자료 (CNY)
A2: 단가가 빈칸이면 금액도 빈칸(견적 필요). 보증금은 회수 가능 자금으로 초기 지출과 분리
A3: 조사 기준일 2026-10-06 · 단위·상태는 각 열 머리글 참조
A5: 비용 ID | B5: 항목 | C5: 유형 | D5: 구조 | E5: 단가(CNY) | F5: 수량 | G5: 주기 | H5: 세금 조건 | I5: 근거 구분 | J5: 회수 가능 | K5: 기준일 | L5: 출처·가정 ID | M5: 금액(CNY) | N5: 산출 상태
A6: CST-001 | B6: 법인 설립 대행·번역·아포스티유 | C6: 초기 | D6: B | F6: 1 | G6: 1회 | H6: 부가세 별도 여부 확인 | I6: 견적 필요 | J6: 아니오 | K6: 2026-10-06 | L6: - | M6: =IF(AND(ISNUMBER(E6),ISNUMBER(F6)),E6*F6,"") | N6: =IF(M6="","견적 필요","산출") -> 견적 필요
A7: CST-002 | B7: 법무·현지 전문가 검토 (등록·허가 의견) | C7: 초기 | D7: B | F7: 1 | G7: 1회 | H7: - | I7: 견적 필요 | J7: 아니오 | K7: 2026-10-06 | L7: - | M7: =IF(AND(ISNUMBER(E7),ISNUMBER(F7)),E7*F7,"") | N7: =IF(M7="","견적 필요","산출") -> 견적 필요
A8: CST-003 | B8: 신규화학물질 등록 (시험·대행) | C8: 초기 | D8: B | F8: 3 | G8: 물질별 | H8: - | I8: 견적 필요 | J8: 아니오 | K8: 2026-10-06 | L8: EVD-006 | M8: =IF(AND(ISNUMBER(E8),ISNUMBER(F8)),E8*F8,"") | N8: =IF(M8="","견적 필요","산출") -> 견적 필요
A9: CST-004 | B9: 위험성 분류 감정·위험화학품 등록 | C9: 초기 | D9: B | F9: 3 | G9: 물질별 | H9: - | I9: 견적 필요 | J9: 아니오 | K9: 2026-10-06 | L9: EVD-018 | M9: =IF(AND(ISNUMBER(E9),ISNUMBER(F9)),E9*F9,"") | N9: =IF(M9="","견적 필요","산출") -> 견적 필요
A10: CST-005 | B10: 안전관리자·책임자 교육·시험 | C10: 초기 | D10: B | F10: 2 | G10: 인 | H10: - | I10: 견적 필요 | J10: 아니오 | K10: 2026-10-06 | L10: EVD-012 | M10: =IF(AND(ISNUMBER(E10),ISNUMBER(F10)),E10*F10,"") | N10: =IF(M10="","견적 필요","산출") -> 견적 필요
A11: CST-006 | B11: 사무실 보증금 | C11: 보증금 | D11: B | E11: =IF(ISNUMBER(OFFICE_RENT),OFFICE_RENT*OFFICE_SQM*DEP_MONTHS,"") | F11: 1 | G11: 1회 | H11: - | I11: 분석 가정 | J11: 예 | K11: 2026-10-06 | L11: ASM-008 | M11: =IF(AND(ISNUMBER(E11),ISNUMBER(F11)),E11*F11,"") | N11: =IF(M11="","견적 필요","산출") -> 견적 필요
A12: CST-007 | B12: 사무 집기·IT·시스템 | C12: 초기 | D12: B | F12: 1 | G12: 1회 | H12: - | I12: 견적 필요 | J12: 아니오 | K12: 2026-10-06 | L12: - | M12: =IF(AND(ISNUMBER(E12),ISNUMBER(F12)),E12*F12,"") | N12: =IF(M12="","견적 필요","산출") -> 견적 필요
A13: CST-008 | B13: 현지 직원 인건비 (기본급×배수×(1+부담률)) | C13: 연간 | D13: B | E13: =BASE_WAGE*WAGE_MULT*(1+ER_RATE) -> 238614.66 | F13: =LOCAL_HC -> 3 | G13: 년 | H13: 세전 | I13: 공개 통계+가정 | J13: - | K13: 2026-10-06 | L13: ASM-002~005 | M13: =IF(AND(ISNUMBER(E13),ISNUMBER(F13)),E13*F13,"") -> 715843.98 | N13: =IF(M13="","공개 통계+가정","산출") -> 산출
A14: CST-009 | B14: 사무실 임대료 | C14: 연간 | D14: B | E14: =IF(ISNUMBER(OFFICE_RENT),OFFICE_RENT*OFFICE_SQM*12,"") | F14: 1 | G14: 년 | H14: 부가세 확인 | I14: 견적 필요 | J14: - | K14: 2026-10-06 | L14: ASM-006, ASM-007 | M14: =IF(AND(ISNUMBER(E14),ISNUMBER(F14)),E14*F14,"") | N14: =IF(M14="","견적 필요","산출") -> 견적 필요
A15: CST-010 | B15: 회계·세무·감사 대행 | C15: 연간 | D15: B | F15: 1 | G15: 년 | H15: - | I15: 견적 필요 | J15: - | K15: 2026-10-06 | L15: - | M15: =IF(AND(ISNUMBER(E15),ISNUMBER(F15)),E15*F15,"") | N15: =IF(M15="","견적 필요","산출") -> 견적 필요
A16: CST-011 | B16: 3PL 위험품 보관·입출고 | C16: 변동 | D16: B | F16: 12 | G16: 월 | H16: - | I16: 견적 필요 | J16: - | K16: 2026-10-06 | L16: SITE-001~005 | M16: =IF(AND(ISNUMBER(E16),ISNUMBER(F16)),E16*F16,"") | N16: =IF(M16="","견적 필요","산출") -> 견적 필요
A17: CST-012 | B17: 위험물 운송 (항만→창고→고객) | C17: 변동 | D17: B | F17: 12 | G17: 월 | H17: - | I17: 견적 필요 | J17: - | K17: 2026-10-06 | L17: - | M17: =IF(AND(ISNUMBER(E17),ISNUMBER(F17)),E17*F17,"") | N17: =IF(M17="","견적 필요","산출") -> 견적 필요
A18: CST-013 | B18: 보험 (제품책임·화물·환경) | C18: 연간 | D18: B | F18: 1 | G18: 년 | H18: - | I18: 견적 필요 | J18: - | K18: 2026-10-06 | L18: - | M18: =IF(AND(ISNUMBER(E18),ISNUMBER(F18)),E18*F18,"") | N18: =IF(M18="","견적 필요","산출") -> 견적 필요
A19: CST-014 | B19: 허가 유지·교육·응급훈련 | C19: 연간 | D19: B | F19: 1 | G19: 년 | H19: - | I19: 견적 필요 | J19: - | K19: 2026-10-06 | L19: EVD-017 | M19: =IF(AND(ISNUMBER(E19),ISNUMBER(F19)),E19*F19,"") | N19: =IF(M19="","견적 필요","산출") -> 견적 필요
A20: CST-015 | B20: 현지 재고 운전자본 (판매액×재고일/30) | C20: 운전자본 | D20: B | E20: =IF(ISNUMBER(MONTHLY_SALES),MONTHLY_SALES*INV_DAYS/30,"") | F20: 1 | G20: - | H20: - | I20: 판매액 미제공 | J20: - | K20: 2026-10-06 | L20: ASM-009, ASM-010 | M20: =IF(AND(ISNUMBER(E20),ISNUMBER(F20)),E20*F20,"") | N20: =IF(M20="","판매액 미제공","산출") -> 판매액 미제공
A21: CST-016 | B21: 주재원 비용 (법인장) | C21: 연간 | D21: B | F21: 1 | G21: 년 | H21: - | I21: 내부 확인 (본사/법인 부담) | J21: - | K21: 2026-10-06 | L21: - | M21: =IF(AND(ISNUMBER(E21),ISNUMBER(F21)),E21*F21,"") | N21: =IF(M21="","내부 확인 (본사/법인 부담)","산출") -> 내부 확인 (본사/법인 부담)
A22: CST-017 | B22: 임차 전용 창고 임대·안전 설비 | C22: 연간 | D22: C | F22: 1 | G22: 년 | H22: - | I22: 견적 필요 | J22: - | K22: 2026-10-06 | L22: - | M22: =IF(AND(ISNUMBER(E22),ISNUMBER(F22)),E22*F22,"") | N22: =IF(M22="","견적 필요","산출") -> 견적 필요
A23: CST-018 | B23: 자체 창고 토지·건설·소방·안전평가 | C23: 초기 | D23: D | F23: 1 | G23: 1회 | H23: - | I23: 견적 필요 | J23: - | K23: 2026-10-06 | L23: - | M23: =IF(AND(ISNUMBER(E23),ISNUMBER(F23)),E23*F23,"") | N23: =IF(M23="","견적 필요","산출") -> 견적 필요

Sheet 15_CostModel
A1: 15_CostModel | 구조별 비용 합계 (B안 최소 구조 기준)
A2: 확인 가능 금액만 합산하고 빈칸 수를 함께 표시 — 부분합을 전체 예산으로 읽지 말 것
A3: 조사 기준일 2026-10-06 · 단위·상태는 각 열 머리글 참조
A5: 구분 | B5: 유형 키 | C5: 확인 가능 합계(CNY) | D5: 견적 필요 건수 | E5: 산출 상태 | F5: KRW 환산(백만원) | G5: 비고
A6: 초기 일회성 비용 | B6: 초기 | C6: =IF(COUNTIFS('14_CostsRaw'!$C$6:$C$23,B6,'14_CostsRaw'!$D$6:$D$23,"B")=D6,"확인분 없음",SUMIFS('14_CostsRaw'!$M$6:$M$23,'14_CostsRaw'!$C$6:$C$23,B6,'14_CostsRaw'!$D$6:$D$23,"B")) -> 확인분 없음 | D6: =COUNTIFS('14_CostsRaw'!$C$6:$C$23,B6,'14_CostsRaw'!$D$6:$D$23,"B",'14_CostsRaw'!$M$6:$M$23,"") -> 6 | E6: =IF(D6>0,"미완성(견적 "&D6&"건)","완성") -> 미완성(견적 6건) | F6: =IF(ISNUMBER(C6),C6*FX_KRW/1000000,"-") -> - | G6: 보증금·재고 제외
A7: 보증금 (회수 가능) | B7: 보증금 | C7: =IF(COUNTIFS('14_CostsRaw'!$C$6:$C$23,B7,'14_CostsRaw'!$D$6:$D$23,"B")=D7,"확인분 없음",SUMIFS('14_CostsRaw'!$M$6:$M$23,'14_CostsRaw'!$C$6:$C$23,B7,'14_CostsRaw'!$D$6:$D$23,"B")) -> 확인분 없음 | D7: =COUNTIFS('14_CostsRaw'!$C$6:$C$23,B7,'14_CostsRaw'!$D$6:$D$23,"B",'14_CostsRaw'!$M$6:$M$23,"") -> 1 | E7: =IF(D7>0,"미완성(견적 "&D7&"건)","완성") -> 미완성(견적 1건) | F7: =IF(ISNUMBER(C7),C7*FX_KRW/1000000,"-") -> - | G7: 현금 지출이나 회수 가능
A8: 연간 고정비 | B8: 연간 | C8: =IF(COUNTIFS('14_CostsRaw'!$C$6:$C$23,B8,'14_CostsRaw'!$D$6:$D$23,"B")=D8,"확인분 없음",SUMIFS('14_CostsRaw'!$M$6:$M$23,'14_CostsRaw'!$C$6:$C$23,B8,'14_CostsRaw'!$D$6:$D$23,"B")) -> 715843.98 | D8: =COUNTIFS('14_CostsRaw'!$C$6:$C$23,B8,'14_CostsRaw'!$D$6:$D$23,"B",'14_CostsRaw'!$M$6:$M$23,"") -> 5 | E8: =IF(D8>0,"미완성(견적 "&D8&"건)","완성") -> 미완성(견적 5건) | F8: =IF(ISNUMBER(C8),C8*FX_KRW/1000000,"-") -> 146.03217 | G8: 인건비·임대·회계 등
A9: 물량 연동 변동비 (연) | B9: 변동 | C9: =IF(COUNTIFS('14_CostsRaw'!$C$6:$C$23,B9,'14_CostsRaw'!$D$6:$D$23,"B")=D9,"확인분 없음",SUMIFS('14_CostsRaw'!$M$6:$M$23,'14_CostsRaw'!$C$6:$C$23,B9,'14_CostsRaw'!$D$6:$D$23,"B")) -> 확인분 없음 | D9: =COUNTIFS('14_CostsRaw'!$C$6:$C$23,B9,'14_CostsRaw'!$D$6:$D$23,"B",'14_CostsRaw'!$M$6:$M$23,"") -> 2 | E9: =IF(D9>0,"미완성(견적 "&D9&"건)","완성") -> 미완성(견적 2건) | F9: =IF(ISNUMBER(C9),C9*FX_KRW/1000000,"-") -> - | G9: 3PL·운송 — 물량 미제공
A10: 운전자본 (재고) | B10: 운전자본 | C10: =IF(COUNTIFS('14_CostsRaw'!$C$6:$C$23,B10,'14_CostsRaw'!$D$6:$D$23,"B")=D10,"확인분 없음",SUMIFS('14_CostsRaw'!$M$6:$M$23,'14_CostsRaw'!$C$6:$C$23,B10,'14_CostsRaw'!$D$6:$D$23,"B")) -> 확인분 없음 | D10: =COUNTIFS('14_CostsRaw'!$C$6:$C$23,B10,'14_CostsRaw'!$D$6:$D$23,"B",'14_CostsRaw'!$M$6:$M$23,"") -> 1 | E10: =IF(D10>0,"미완성(견적 "&D10&"건)","완성") -> 미완성(견적 1건) | F10: =IF(ISNUMBER(C10),C10*FX_KRW/1000000,"-") -> - | G10: 판매액 미제공
A12: 인건비 시나리오 (1인당 연 인건비 × 인원)
A13: 시나리오 | B13: 현지 인원 | C13: 1인당 연 인건비(CNY) | D13: 연 인건비(CNY) | E13: KRW(백만원) | F13: 구성 | G13: 상태
A14: 최소 (B안) | B14: =LOCAL_HC -> 3 | C14: =BASE_WAGE*WAGE_MULT*(1+ER_RATE) -> 238614.66 | D14: =B14*C14 -> 715843.98 | E14: =D14*FX_KRW/1000000 -> 146.03217 | F14: 안전관리자·영업·경리 + 법인장(주재원 별도) | G14: 분석 가정 (평균임금 기반)
A15: 기준 (B안+물류) | B15: =LOCAL_HC+1 -> 4 | C15: =BASE_WAGE*WAGE_MULT*(1+ER_RATE) -> 238614.66 | D15: =B15*C15 -> 954458.64 | E15: =D15*FX_KRW/1000000 -> 194.70956 | F15: +수입·물류·통관 | G15: 분석 가정 (평균임금 기반)
A16: 확대 (C안) | B16: =LOCAL_HC+3 -> 6 | C16: =BASE_WAGE*WAGE_MULT*(1+ER_RATE) -> 238614.66 | D16: =B16*C16 -> 1431688 | E16: =D16*FX_KRW/1000000 -> 292.06434 | F16: +물류 1·창고·품질 2 | G16: 분석 가정 (평균임금 기반)
A18: 등록자본 제안 (가정)
A19: 확인 가능 연간 고정비 × 배수 | C19: =C8*CAP_MULT -> 1073766 | E19: =IF(D8>0,"미완성 — 임대·회계·주재원 견적 반영 후 재산정","산정") -> 미완성 — 임대·회계·주재원 견적 반영 후 재산정 | F19: =C19*FX_KRW/1000000 -> 219.04826 | G19: 법정 최저자본 아님. 5년 내 납입(공사법). 등록자본·투자비·보증금·재고자금은 서로 다른 개념
A21: 손익분기 산식 (매출·마진 미제공 → 산식만)
A22: 필요 연 매출총이익 = 연간 고정비 + 변동비 (견적 반영 후)
A23: 필요 연 매출 = 필요 매출총이익 ÷ 매출총이익률 (내부 입력)

Sheet 16_Timeline
A1: 16_Timeline | 일정 (2026-10-06 착수, 주 단위 · 달력일 기준)
A2: 선행 작업의 최대 종료일 다음 날 시작. 공휴일 미반영 → 영업일 일정 아님. 기간은 분석 가정
A3: 조사 기준일 2026-10-06 · 단위·상태는 각 열 머리글 참조
B4: 착수일 | C4: 46301
A5: 작업 ID | B5: 단계 | C5: 구조 | D5: 책임 부서 | E5: 산출물 | F5: 선행1 | G5: 선행2 | H5: 기간 낙관(주) | I5: 기간 기준(주) | J5: 기간 보수(주) | K5: 시작(기준) | L5: 종료(기준) | M5: 종료(기준)·참조용 | N5: 종료(낙관) | O5: 종료(보수) | P5: 기간 근거 | Q5: 법정·현실 | R5: 병목 | S5: 시작(낙관) | T5: 시작(보수)
A6: T01 | B6: 대상 물질·규제 분류 확정 (CAS·SDS·备案 현황) | C6: 공통 | D6: 해외영업·한호진 PL | E6: 제품별 판정표 | H6: 1 | I6: 2 | J6: 3 | K6: =MAX(IF(F6="",T0-1,INDEX($L$6:$L$20,MATCH(F6,$A$6:$A$20,0))),IF(G6="",T0-1,INDEX($L$6:$L$20,MATCH(G6,$A$6:$A$20,0))))+1 -> 46301 | L6: =K6+I6*7-1 -> 46314 | M6: =L6 -> 46314 | N6: =S6+H6*7-1 -> 46307 | O6: =T6+J6*7-1 -> 46321 | P6: 내부 자료 수집 | Q6: 현실 | R6: 备案 보유자 확인 | S6: =MAX(IF(F6="",T0-1,INDEX($N$6:$N$20,MATCH(F6,$A$6:$A$20,0))),IF(G6="",T0-1,INDEX($N$6:$N$20,MATCH(G6,$A$6:$A$20,0))))+1 -> 46301 | T6: =MAX(IF(F6="",T0-1,INDEX($O$6:$O$20,MATCH(F6,$A$6:$A$20,0))),IF(G6="",T0-1,INDEX($O$6:$O$20,MATCH(G6,$A$6:$A$20,0))))+1 -> 46301
A7: T02 | B7: MP 현황 확인 (허가·창고·등록 능력) | C7: A | D7: 해외영업·기획 | E7: MP 실사표 | H7: 1 | I7: 2 | J7: 3 | K7: =MAX(IF(F7="",T0-1,INDEX($L$6:$L$20,MATCH(F7,$A$6:$A$20,0))),IF(G7="",T0-1,INDEX($L$6:$L$20,MATCH(G7,$A$6:$A$20,0))))+1 -> 46301 | L7: =K7+I7*7-1 -> 46314 | M7: =L7 -> 46314 | N7: =S7+H7*7-1 -> 46307 | O7: =T7+J7*7-1 -> 46321 | P7: 내부 질의 | Q7: 현실 | R7: - | S7: =MAX(IF(F7="",T0-1,INDEX($N$6:$N$20,MATCH(F7,$A$6:$A$20,0))),IF(G7="",T0-1,INDEX($N$6:$N$20,MATCH(G7,$A$6:$A$20,0))))+1 -> 46301 | T7: =MAX(IF(F7="",T0-1,INDEX($O$6:$O$20,MATCH(F7,$A$6:$A$20,0))),IF(G7="",T0-1,INDEX($O$6:$O$20,MATCH(G7,$A$6:$A$20,0))))+1 -> 46301
A8: T03 | B8: 기관 질의 (무석 신오구·생태환경부·3PL) | C8: 공통 | D8: 중국 현지·법무 | E8: 질의 회신 | H8: 2 | I8: 3 | J8: 5 | K8: =MAX(IF(F8="",T0-1,INDEX($L$6:$L$20,MATCH(F8,$A$6:$A$20,0))),IF(G8="",T0-1,INDEX($L$6:$L$20,MATCH(G8,$A$6:$A$20,0))))+1 -> 46301 | L8: =K8+I8*7-1 -> 46321 | M8: =L8 -> 46321 | N8: =S8+H8*7-1 -> 46314 | O8: =T8+J8*7-1 -> 46335 | P8: 회신 대기 | Q8: 현실 | R8: 기관 회신 | S8: =MAX(IF(F8="",T0-1,INDEX($N$6:$N$20,MATCH(F8,$A$6:$A$20,0))),IF(G8="",T0-1,INDEX($N$6:$N$20,MATCH(G8,$A$6:$A$20,0))))+1 -> 46301 | T8: =MAX(IF(F8="",T0-1,INDEX($O$6:$O$20,MATCH(F8,$A$6:$A$20,0))),IF(G8="",T0-1,INDEX($O$6:$O$20,MATCH(G8,$A$6:$A$20,0))))+1 -> 46301
A9: T04 | B9: 법무·현지 전문가 검토 | C9: 공통 | D9: 법무 | E9: 법률 의견서 | F9: T01 | H9: 2 | I9: 3 | J9: 4 | K9: =MAX(IF(F9="",T0-1,INDEX($L$6:$L$20,MATCH(F9,$A$6:$A$20,0))),IF(G9="",T0-1,INDEX($L$6:$L$20,MATCH(G9,$A$6:$A$20,0))))+1 -> 46315 | L9: =K9+I9*7-1 -> 46335 | M9: =L9 -> 46335 | N9: =S9+H9*7-1 -> 46321 | O9: =T9+J9*7-1 -> 46349 | P9: 외부 전문가 | Q9: 현실 | R9: - | S9: =MAX(IF(F9="",T0-1,INDEX($N$6:$N$20,MATCH(F9,$A$6:$A$20,0))),IF(G9="",T0-1,INDEX($N$6:$N$20,MATCH(G9,$A$6:$A$20,0))))+1 -> 46308 | T9: =MAX(IF(F9="",T0-1,INDEX($O$6:$O$20,MATCH(F9,$A$6:$A$20,0))),IF(G9="",T0-1,INDEX($O$6:$O$20,MATCH(G9,$A$6:$A$20,0))))+1 -> 46322
A10: T05 | B10: 경영진 승인 (구조·지역·예산) | C10: 공통 | D10: 기획 | E10: 승인 | F10: T03 | G10: T04 | H10: 1 | I10: 1 | J10: 2 | K10: =MAX(IF(F10="",T0-1,INDEX($L$6:$L$20,MATCH(F10,$A$6:$A$20,0))),IF(G10="",T0-1,INDEX($L$6:$L$20,MATCH(G10,$A$6:$A$20,0))))+1 -> 46336 | L10: =K10+I10*7-1 -> 46342 | M10: =L10 -> 46342 | N10: =S10+H10*7-1 -> 46328 | O10: =T10+J10*7-1 -> 46363 | P10: 내부 | Q10: 현실 | R10: - | S10: =MAX(IF(F10="",T0-1,INDEX($N$6:$N$20,MATCH(F10,$A$6:$A$20,0))),IF(G10="",T0-1,INDEX($N$6:$N$20,MATCH(G10,$A$6:$A$20,0))))+1 -> 46322 | T10: =MAX(IF(F10="",T0-1,INDEX($O$6:$O$20,MATCH(F10,$A$6:$A$20,0))),IF(G10="",T0-1,INDEX($O$6:$O$20,MATCH(G10,$A$6:$A$20,0))))+1 -> 46350
A11: T06 | B11: 한국 해외직접투자 신고·송금 | C11: B | D11: 기획·재무 | E11: 신고 수리 | F11: T05 | H11: 1 | I11: 1 | J11: 2 | K11: =MAX(IF(F11="",T0-1,INDEX($L$6:$L$20,MATCH(F11,$A$6:$A$20,0))),IF(G11="",T0-1,INDEX($L$6:$L$20,MATCH(G11,$A$6:$A$20,0))))+1 -> 46343 | L11: =K11+I11*7-1 -> 46349 | M11: =L11 -> 46349 | N11: =S11+H11*7-1 -> 46335 | O11: =T11+J11*7-1 -> 46377 | P11: 은행 절차 | Q11: 현실 | R11: - | S11: =MAX(IF(F11="",T0-1,INDEX($N$6:$N$20,MATCH(F11,$A$6:$A$20,0))),IF(G11="",T0-1,INDEX($N$6:$N$20,MATCH(G11,$A$6:$A$20,0))))+1 -> 46329 | T11: =MAX(IF(F11="",T0-1,INDEX($O$6:$O$20,MATCH(F11,$A$6:$A$20,0))),IF(G11="",T0-1,INDEX($O$6:$O$20,MATCH(G11,$A$6:$A$20,0))))+1 -> 46364
A12: T07 | B12: 법인 등기 (营业执照) | C12: B | D12: 법무·현지 | E12: 营业执照 | F12: T05 | H12: 3 | I12: 5 | J12: 8 | K12: =MAX(IF(F12="",T0-1,INDEX($L$6:$L$20,MATCH(F12,$A$6:$A$20,0))),IF(G12="",T0-1,INDEX($L$6:$L$20,MATCH(G12,$A$6:$A$20,0))))+1 -> 46343 | L12: =K12+I12*7-1 -> 46377 | M12: =L12 -> 46377 | N12: =S12+H12*7-1 -> 46349 | O12: =T12+J12*7-1 -> 46419 | P12: 서류 아포스티유 포함 가정 | Q12: 현실 | R12: 주소·서류 | S12: =MAX(IF(F12="",T0-1,INDEX($N$6:$N$20,MATCH(F12,$A$6:$A$20,0))),IF(G12="",T0-1,INDEX($N$6:$N$20,MATCH(G12,$A$6:$A$20,0))))+1 -> 46329 | T12: =MAX(IF(F12="",T0-1,INDEX($O$6:$O$20,MATCH(F12,$A$6:$A$20,0))),IF(G12="",T0-1,INDEX($O$6:$O$20,MATCH(G12,$A$6:$A$20,0))))+1 -> 46364
A13: T08 | B13: 계좌·외환·세무·해관 등록 | C13: B | D13: 재무·현지 | E13: 등록 완료 | F13: T07 | H13: 2 | I13: 3 | J13: 5 | K13: =MAX(IF(F13="",T0-1,INDEX($L$6:$L$20,MATCH(F13,$A$6:$A$20,0))),IF(G13="",T0-1,INDEX($L$6:$L$20,MATCH(G13,$A$6:$A$20,0))))+1 -> 46378 | L13: =K13+I13*7-1 -> 46398 | M13: =L13 -> 46398 | N13: =S13+H13*7-1 -> 46363 | O13: =T13+J13*7-1 -> 46454 | P13: 기관 실무 | Q13: 현실 | R13: - | S13: =MAX(IF(F13="",T0-1,INDEX($N$6:$N$20,MATCH(F13,$A$6:$A$20,0))),IF(G13="",T0-1,INDEX($N$6:$N$20,MATCH(G13,$A$6:$A$20,0))))+1 -> 46350 | T13: =MAX(IF(F13="",T0-1,INDEX($O$6:$O$20,MATCH(F13,$A$6:$A$20,0))),IF(G13="",T0-1,INDEX($O$6:$O$20,MATCH(G13,$A$6:$A$20,0))))+1 -> 46420
A14: T09 | B14: 무저장 위험화학품 경영허가 | C14: B | D14: 현지·안전관리자 | E14: 경영허가증 | F14: T07 | H14: 5 | I14: 8 | J14: 12 | K14: =MAX(IF(F14="",T0-1,INDEX($L$6:$L$20,MATCH(F14,$A$6:$A$20,0))),IF(G14="",T0-1,INDEX($L$6:$L$20,MATCH(G14,$A$6:$A$20,0))))+1 -> 46378 | L14: =K14+I14*7-1 -> 46433 | M14: =L14 -> 46433 | N14: =S14+H14*7-1 -> 46384 | O14: =T14+J14*7-1 -> 46503 | P14: 법정 20 영업일(사례)+준비 | Q14: 법정+준비 | R14: 안전관리자 채용·시험 | S14: =MAX(IF(F14="",T0-1,INDEX($N$6:$N$20,MATCH(F14,$A$6:$A$20,0))),IF(G14="",T0-1,INDEX($N$6:$N$20,MATCH(G14,$A$6:$A$20,0))))+1 -> 46350 | T14: =MAX(IF(F14="",T0-1,INDEX($O$6:$O$20,MATCH(F14,$A$6:$A$20,0))),IF(G14="",T0-1,INDEX($O$6:$O$20,MATCH(G14,$A$6:$A$20,0))))+1 -> 46420
A15: T10 | B15: 수입기업 위험화학품 등록 | C15: B | D15: 현지 | E15: 등록증 | F15: T09 | H15: 2 | I15: 4 | J15: 6 | K15: =MAX(IF(F15="",T0-1,INDEX($L$6:$L$20,MATCH(F15,$A$6:$A$20,0))),IF(G15="",T0-1,INDEX($L$6:$L$20,MATCH(G15,$A$6:$A$20,0))))+1 -> 46434 | L15: =K15+I15*7-1 -> 46461 | M15: =L15 -> 46461 | N15: =S15+H15*7-1 -> 46398 | O15: =T15+J15*7-1 -> 46545 | P15: 기관 확인 | Q15: 현실 | R15: 분류 감정 | S15: =MAX(IF(F15="",T0-1,INDEX($N$6:$N$20,MATCH(F15,$A$6:$A$20,0))),IF(G15="",T0-1,INDEX($N$6:$N$20,MATCH(G15,$A$6:$A$20,0))))+1 -> 46385 | T15: =MAX(IF(F15="",T0-1,INDEX($O$6:$O$20,MATCH(F15,$A$6:$A$20,0))),IF(G15="",T0-1,INDEX($O$6:$O$20,MATCH(G15,$A$6:$A$20,0))))+1 -> 46504
A16: T11 | B16: 신규화학물질 등록 (TC 법인 명의) | C16: B | D16: 법무·한호진 PL | E16: 등록증 | F16: T07 | H16: 12 | I16: 20 | J16: 32 | K16: =MAX(IF(F16="",T0-1,INDEX($L$6:$L$20,MATCH(F16,$A$6:$A$20,0))),IF(G16="",T0-1,INDEX($L$6:$L$20,MATCH(G16,$A$6:$A$20,0))))+1 -> 46378 | L16: =K16+I16*7-1 -> 46517 | M16: =L16 -> 46517 | N16: =S16+H16*7-1 -> 46433 | O16: =T16+J16*7-1 -> 46643 | P16: 시험·심사(간이 준용) | Q16: 법정+시험 | R16: 중국 내 시험 | S16: =MAX(IF(F16="",T0-1,INDEX($N$6:$N$20,MATCH(F16,$A$6:$A$20,0))),IF(G16="",T0-1,INDEX($N$6:$N$20,MATCH(G16,$A$6:$A$20,0))))+1 -> 46350 | T16: =MAX(IF(F16="",T0-1,INDEX($O$6:$O$20,MATCH(F16,$A$6:$A$20,0))),IF(G16="",T0-1,INDEX($O$6:$O$20,MATCH(G16,$A$6:$A$20,0))))+1 -> 46420
A17: T12 | B17: 3PL 창고 계약·품목 확인 | C17: B | D17: 현지·물류 | E17: 계약 | F17: T03 | H17: 4 | I17: 6 | J17: 10 | K17: =MAX(IF(F17="",T0-1,INDEX($L$6:$L$20,MATCH(F17,$A$6:$A$20,0))),IF(G17="",T0-1,INDEX($L$6:$L$20,MATCH(G17,$A$6:$A$20,0))))+1 -> 46322 | L17: =K17+I17*7-1 -> 46363 | M17: =L17 -> 46363 | N17: =S17+H17*7-1 -> 46342 | O17: =T17+J17*7-1 -> 46405 | P17: 운영사 협의 | Q17: 현실 | R17: 4.2·4.3류 수용 | S17: =MAX(IF(F17="",T0-1,INDEX($N$6:$N$20,MATCH(F17,$A$6:$A$20,0))),IF(G17="",T0-1,INDEX($N$6:$N$20,MATCH(G17,$A$6:$A$20,0))))+1 -> 46315 | T17: =MAX(IF(F17="",T0-1,INDEX($O$6:$O$20,MATCH(F17,$A$6:$A$20,0))),IF(G17="",T0-1,INDEX($O$6:$O$20,MATCH(G17,$A$6:$A$20,0))))+1 -> 46336
A18: T13 | B18: 고객 공급자 변경 승인 | C18: B | D18: 해외영업 | E18: 승인 | F18: T10 | G18: T11 | H18: 4 | I18: 8 | J18: 12 | K18: =MAX(IF(F18="",T0-1,INDEX($L$6:$L$20,MATCH(F18,$A$6:$A$20,0))),IF(G18="",T0-1,INDEX($L$6:$L$20,MATCH(G18,$A$6:$A$20,0))))+1 -> 46518 | L18: =K18+I18*7-1 -> 46573 | M18: =L18 -> 46573 | N18: =S18+H18*7-1 -> 46461 | O18: =T18+J18*7-1 -> 46727 | P18: 고객 절차 | Q18: 현실 | R18: 고객 승인 | S18: =MAX(IF(F18="",T0-1,INDEX($N$6:$N$20,MATCH(F18,$A$6:$A$20,0))),IF(G18="",T0-1,INDEX($N$6:$N$20,MATCH(G18,$A$6:$A$20,0))))+1 -> 46434 | T18: =MAX(IF(F18="",T0-1,INDEX($O$6:$O$20,MATCH(F18,$A$6:$A$20,0))),IF(G18="",T0-1,INDEX($O$6:$O$20,MATCH(G18,$A$6:$A$20,0))))+1 -> 46644
A19: T14 | B19: 초도 공급 | C19: B | D19: 해외영업·물류 | E19: 첫 납품 | F19: T12 | G19: T13 | H19: 1 | I19: 2 | J19: 3 | K19: =MAX(IF(F19="",T0-1,INDEX($L$6:$L$20,MATCH(F19,$A$6:$A$20,0))),IF(G19="",T0-1,INDEX($L$6:$L$20,MATCH(G19,$A$6:$A$20,0))))+1 -> 46574 | L19: =K19+I19*7-1 -> 46587 | M19: =L19 -> 46587 | N19: =S19+H19*7-1 -> 46468 | O19: =T19+J19*7-1 -> 46748 | P19: - | Q19: 현실 | R19: - | S19: =MAX(IF(F19="",T0-1,INDEX($N$6:$N$20,MATCH(F19,$A$6:$A$20,0))),IF(G19="",T0-1,INDEX($N$6:$N$20,MATCH(G19,$A$6:$A$20,0))))+1 -> 46462 | T19: =MAX(IF(F19="",T0-1,INDEX($O$6:$O$20,MATCH(F19,$A$6:$A$20,0))),IF(G19="",T0-1,INDEX($O$6:$O$20,MATCH(G19,$A$6:$A$20,0))))+1 -> 46728
A20: T20 | B20: [연말 대응] 기존 备案 보유자 전환 신청 | C20: G | D20: 해외영업·법무 | E20: 전환 신청 접수 | F20: T01 | H20: 4 | I20: 6 | J20: 10 | K20: =MAX(IF(F20="",T0-1,INDEX($L$6:$L$20,MATCH(F20,$A$6:$A$20,0))),IF(G20="",T0-1,INDEX($L$6:$L$20,MATCH(G20,$A$6:$A$20,0))))+1 -> 46315 | L20: =K20+I20*7-1 -> 46356 | M20: =L20 -> 46356 | N20: =S20+H20*7-1 -> 46335 | O20: =T20+J20*7-1 -> 46391 | P20: 12-31 기한(EVD-003) | Q20: 법정 기한 | R20: 보유자 협조 | S20: =MAX(IF(F20="",T0-1,INDEX($N$6:$N$20,MATCH(F20,$A$6:$A$20,0))),IF(G20="",T0-1,INDEX($N$6:$N$20,MATCH(G20,$A$6:$A$20,0))))+1 -> 46308 | T20: =MAX(IF(F20="",T0-1,INDEX($O$6:$O$20,MATCH(F20,$A$6:$A$20,0))),IF(G20="",T0-1,INDEX($O$6:$O$20,MATCH(G20,$A$6:$A$20,0))))+1 -> 46322

Sheet 17_RisksActions
A1: 17_RisksActions | 리스크·확인 과제
A2: 기한은 착수 후 2~6주 내 제안 일정. 진행 상태는 모두 '문의 예정'
A3: 조사 기준일 2026-10-06 · 단위·상태는 각 열 머리글 참조
A5: 리스크 ID | B5: 내용 | C5: 영향 | D5: 현재 근거 | E5: 확인 대상 | F5: 담당 부서 | G5: 우선순위 | H5: 대응 | I5: 기한 | J5: 진행 상태 | K5: 완료 증거 | L5: PPT 페이지
A6: R01 | B6: 등록 주체 오판 (개정안 확정 시 해외 기업 신청 불가) | C6: 높음 | D6: EVD-002 (초안) | E6: 생태환경부·법무 | F6: 법무 | G6: 1 | H6: 최종 공포 여부 확인, TC 법인·대리 두 경로 병행 | I6: 2026-10-20 | J6: 문의 예정 | K6: - | L6: 27
A7: R02 | B7: 연말 기한 대상 여부 오판 (备案 보유 여부) | C7: 높음 | D7: EVD-003 | E7: 고객·기존 대리인 | F7: 해외영업 | G7: 1 | H7: 备案 번호·보유자 확인 후 전환 신청 | I7: 2026-10-16 | J7: 문의 예정 | K7: - | L7: 27
A8: R03 | B8: 제품 분류 오류 (위험화학품·신규 여부) | C8: 높음 | D8: 정보 없음 | E8: SDS·IECSC 검색 | F8: 한호진 PL | G8: 1 | H8: 제품별 판정표 작성·감정 | I8: 2026-10-20 | J8: 문의 예정 | K8: - | L8: 27
A9: R04 | B9: 강소성 원구·창고 진입 불가 | C9: 중간 | D9: EVD-020 (원구 존재만 확인) | E9: 원구·3PL | F9: 현지 | G9: 2 | H9: 무석·장자강·상하이 3PL 동시 질의 | I9: 2026-10-31 | J9: 문의 예정 | K9: - | L9: 27
A10: R05 | B10: 4.2·4.3류 등 특수 물성 수용 창고 미확보 | C10: 높음 | D10: 정보 없음 | E10: 3PL | F10: 현지·물류 | G10: 1 | H10: 물성 확정 후 품목 범위 확인 | I10: 2026-10-31 | J10: 문의 예정 | K10: - | L10: 27
A11: R06 | B11: 수입·운송 제한 (항만 위험물 범위·차량 통행) | C11: 중간 | D11: 정보 없음 | E11: 항만·운송사 | F11: 물류 | G11: 2 | H11: 수입항·경로 사전 확인 | I11: 2026-11-15 | J11: 문의 예정 | K11: - | L11: 27
A12: R07 | B12: IP·시험자료 사용권 (한국 자료 권리) | C12: 중간 | D12: EVD-006 | E12: 내부 법무 | F12: 법무 | G12: 2 | H12: 자료 목록·소유권 정리, 정보보호 신청 | I12: 2026-10-31 | J12: 문의 예정 | K12: - | L12: 27
A13: R08 | B13: 등록증 명의 이관 (대리·MP → TC) | C13: 중간 | D13: EVD-005 | E13: 생태환경부 | F13: 법무 | G13: 2 | H13: 처음부터 최종 명의자로 신청 | I13: 2026-10-31 | J13: 문의 예정 | K13: - | L13: 27
A14: R09 | B14: 고객 공급자 변경 승인 지연 | C14: 중간 | D14: 정보 없음 | E14: 고객 | F14: 해외영업 | G14: 2 | H14: 고객별 승인 절차 사전 협의 | I14: 2026-11-15 | J14: 문의 예정 | K14: - | L14: 27
A15: R10 | B15: 중국 내 시험 지연 (공시생물 생태독성) | C15: 중간 | D15: EVD-006 | E15: 시험기관 | F15: 한호진 PL | G15: 2 | H15: 시험기관 견적·일정 확보 | I15: 2026-10-31 | J15: 문의 예정 | K15: - | L15: 27
A16: R11 | B16: 외자 자금 운용·회수 제약 오해 | C16: 낮음 | D16: EVD-022, EVD-035 | E16: 재무·은행 | F16: 기획 | G16: 3 | H16: 자본금 규모·회수 경로 설계 | I16: 2026-11-15 | J16: 문의 예정 | K16: - | L16: 27
... A18: R13 | B18: MP 정보 부족으로 비교 불가 | C18: 중간 | D18: MP 표 대부분 정보 없음 | E18: MP | F18: 기획 | G18: 1 | H18: MP 실사 질문지 회신 | I18: 2026-10-16 | J18: 문의 예정 | K18: - | L18: 27

Sheet 18_PPTTraceability
A1: 18_PPTTraceability | PPT ↔ 근거 추적
A2: PPT 주요 주장과 숫자의 근거 시트·ID
A3: 조사 기준일 2026-10-06 · 단위·상태는 각 열 머리글 참조
A5: PPT 페이지 | B5: 슬라이드 | C5: 핵심 주장 | D5: 숫자·비교 결과 | E5: 원자료 시트 | F5: 근거 ID | G5: 출처 ID | H5: 가정 ID | I5: 조건·한계 | J5: 검증 상태
A6: 02 | B6: 경영진 요약 | C6: B안·무석 조건부 추천 / 연말 기한 / 등록 주체 | D6: B안 비용(확인 가능분) | E6: 02_ExecutiveSummary, 15_CostModel | F6: EVD-002, EVD-003, EVD-014 | G6: SRC-004, SRC-005, SRC-011 | H6: ASM-001~011 | I6: 조건부 | J6: 근거 기반·기관 확인 전
A7: 05 | B7: 회의 가설 검증 | C7: 5개 주장 검증 결과 | D7: - | E7: 06_LegalMatrix | F7: EVD-001~011 | G7: SRC-001, SRC-005, SRC-009 | H7: - | I7: 개정안 확정 여부 | J7: 요약 확인
A8: 10 | B8: 화학물질 등록·IP | C8: 신청 주체·시험자료·정보보호 | D8: - | E8: 06_LegalMatrix | F8: EVD-001~007 | G8: SRC-001~008, SRC-036, SRC-040 | H8: - | I8: - | J8: 요약 확인
A9: 11 | B9: 위험화학품 허가 경로 | C9: 무저장·임차저장·저장 / 처리기한 | D9: 20 영업일(사례) | E9: 07_PermitPaths | F9: EVD-008~018 | G9: SRC-009~011, SRC-035 | H9: - | I9: 무석 기한 확인 | J9: 요약 확인
A10: 13~18 | B10: 강소성 후보 | C10: 원구 23곳·무석·쑤저우·창저우 | D10: 점수 76/69/63 | E10: 08_CityComparison, 09_SitesWarehouses | F10: EVD-020, EVD-021 | G10: SRC-013, SRC-030 | H10: 점수 가정 | I10: 점수=분석 가정 | J10: 근거 기반
A11: 20~22 | B11: 인근 대안·민감도 | C11: 상하이·허페이 / 가중치 3세트 | D11: 점수 68 등 | E11: 08_CityComparison | F11: SRC-031~034 | G11: - | H11: 가중치 | I11: - | J11: 근거 부족
A12: 23 | B12: MP vs TC | C12: 시나리오 1·2 | D12: - | E12: 11_MPComparison | F12: EVD-002, EVD-005 | G12: - | H12: - | I12: MP 정보 없음 | J12: 내부 확인 필요
A13: 25 | B13: 비용 | C13: 초기·연간·인건비·등록자본 | D13: 15 시트 값 | E13: 15_CostModel, 14_CostsRaw, 13_FXAssumptions | F13: EVD-027, EVD-034, EVD-036 | G13: SRC-024~026 | H13: ASM-001~011 | I13: 견적 필요 다수 | J13: 미완성
A14: 26 | B14: 일정 | C14: 기준 시나리오·연말 대응 | D14: 16 시트 값 | E14: 16_Timeline | F14: EVD-003, EVD-016 | G14: SRC-005, SRC-035 | H14: 기간 가정 | I14: 공휴일 미반영 | J14: 분석 가정
A15: 27 | B15: 리스크·2주 과제 | C15: R01~R13 | D15: - | E15: 17_RisksActions | F15: - | G15: - | H15: - | I15: - | J15: 문의 예정

Sheet 19_Glossary_Q
A1: 19_Glossary_Q | 용어 해설·질문지
A2: 부록 용어표·기관 질문지 원본
A3: 조사 기준일 2026-10-06 · 단위·상태는 각 열 머리글 참조
A5: 용어 | B5: 쉬운 뜻 | C5: 이번 사업과의 관계
A6: 신규화학물질 등록 (新化学物质环境管理登记) | B6: 중국 기존화학물질 목록(IECSC)에 없는 물질을 만들거나 수입하기 전에 생태환경부에 받는 등록 | C6: Y·Sc·La 전구체가 목록에 없으면 수입 전 필요
A7: 备案 (소량 신고) | B7: 종전 1톤 미만 등 소량 신규물질에 쓰던 간단한 신고. 2026-08-15 접수 중단 | C7: 기존 备案은 2026-12-31까지 등록증으로 전환
A8: 간이등록 (简易登记) | B8: 연 1~10톤 신규물질 등록. 시험자료 일부 필요 | C8: 备案 전환도 이 절차를 준용
A9: 위험화학품 (危险化学品) | B9: 중국 위험화학품 목록 등에 해당해 별도 안전관리를 받는 화학품 | C9: 해당 시 판매 허가·창고·운송 규제
A10: 위험화학품 경영허가 (经营许可) | B10: 위험화학품을 사고파는 회사가 받는 판매 허가 | C10: TC 중국법인이 판매자면 필요
A11: 무저장 경영 (无储存经营) | B11: 자체 창고 없이 계약·세금계산서로만 거래하는 경영 방식 | C11: 최소 투자안(B안)의 기본
A12: 임차저장 경영 (租赁储存经营) | B12: 허가 창고를 빌려 저장하며 경영하는 방식 (무석 세칙 구분) | C12: C안
A13: 수입자 (进口者/收货人) | B13: 통관 서류상 물품을 들여오는 회사. 위험화학품 등록·중문 SDS 책임 | C13: 수입 명의가 곧 책임 주체
A14: 등록 신청 주체 | B14: 신규화학물질 등록증의 명의자. 의무·책임과 자료 통제권을 가짐 | C14: 개정안 확정 시 중국 수입기업만 가능
A15: 외부 창고 (3PL) | B15: 위험품 보관 허가를 가진 물류회사 창고를 계약해 쓰는 것 | C15: 허가 범위는 창고 운영사에 귀속
A16: 화공원구 (化工园区) | B16: 성 정부가 인정한 화학산업 단지. 위험화학품 생산·저장 시설이 모이는 곳 | C16: 강소성 신규 저장은 원구 내가 현실적
... A19: 아포스티유 | B19: 외국 공문서 인증 간소화 확인서. 중국 2023-11-07 발효 | C19: 한국 본사 서류 준비 기간 단축
A22: 질문지 (진행 상태: 모두 문의 예정)
A23: A. 중국 법률·등록 전문가
B24: 12호령 개정안(2026-06 초안)은 최종 공포됐는가? 신청 주체를 중국 내 생산·수입 기업으로 한정하는 조항이 확정됐는가? | C24: 문의 예정
B25: 환판고체함〔2026〕301호의 '2026-12-31까지 등록증 취득' 의무는 누구(备案 신청인)에게 적용되며, 미취득 시 수입·사용 제한·처벌 근거는? | C25: 문의 예정
B26: 현행 규정에서 TC 본사(해외 생산자)+대리인으로 등록 후 TC 중국법인으로 명의를 바꿀 수 있는가? 재신청이 필요한가? | C26: 문의 예정
B27: 한국에서 수행한 시험자료 중 인정 가능한 항목과 중국 내 보완 시험(공시생물) 목록은? | C27: 문의 예정
B28: 수입·판매·외부 창고 보관만 할 때 생산허가·생산설비 요구 근거가 있는가? 충진·소분은 어디부터 생산/분장 경영인가? | C28: 문의 예정
B29: 위험화학품안전법 시행(2026-05-01) 후 경영허가 하위 규정(55호령) 개정·경과조치는? | C29: 문의 예정
A30: B. 도시·산업단지 (무석 신오구 등)
B31: 외국인 독자 화학품 무역법인(무저장 경영) 설립·허가 관할 부서와 처리기한은? | C31: 문의 예정
B32: 무저장 경영 사무 장소 요건(용도·면적·소방)과 전담 안전관리자 요건은? | C32: 문의 예정
B33: 임차저장 경영 시 임차 창고가 무석 관할 밖(장자강·상하이)이어도 되는가? | C33: 문의 예정
B34: 인정 화공원구(江阴临港·锡山·宜兴) 내 위험품 창고 임차·입주 조건, 외자 소규모 무역법인 수용 여부는? | C34: 문의 예정
B35: 자연발화·수분반응 물질(4.2·4.3류 가능성) 보관 가능한 창고가 관내에 있는가? | C35: 문의 예정
A36: C. 창고·운송사
B37: 위험화학품 경영(저장/창고) 허가증 사본과 허가 품목 범위는? | C37: 문의 예정
B38: 자연발화·수분반응 물질, 불활성가스 봉입 용기 보관 가능 여부와 수량 제한은? | C38: 문의 예정
B39: 보험·책임 범위, 재고 관리 시스템, 온습도 관리, 출입 통제는? | C39: 문의 예정
B40: 항만(상하이·장자강) 수입 → 창고 → 고객(무석·허페이) 위험물 운송 가능 여부와 리드타임·견적은? | C40: 문의 예정
B41: 공병 회수·잔류물 처리·국제 반송 대응 가능 여부는? | C41: 문의 예정
A42: D. MP
B43: 정식 법인명·주소·지분·사업범위(营业执照) 및 위험화학품 경영허가 보유 여부·품목·저장 방식은? | C43: 문의 예정
B44: 수입기업 위험화학품 등록·신규화학물질 등록(또는 备案) 수행 실적은? | C44: 문의 예정
B45: 창고 보유 여부·허가 범위, TC 제품 취급에 필요한 추가 투자·기간은? | C45: 문의 예정
B46: TC 업무 지원 가능 인원·일정, 서비스 대가·책임 분담·자료 접근 통제 방안은? | C46: 문의 예정
A47: E. SKTC 내부
B48: Y·Sc·La 전구체 각각의 제품명·화학명·CAS·조성·SDS·연간 중국 수입량(샘플/양산 구분)은? | C48: 문의 예정
B49: 현재 중국 수입자·备案/등록 보유자(번호)는 누구인가? 연말 전환 대상인가? | C49: 문의 예정
B50: 보유 시험자료 목록·시험기관·GLP 여부·소유권(공동시험 포함)은? | C50: 문의 예정
B51: 고객별 공급 구조(직판/유통사), 고객 승인 공급자 변경 절차는? | C51: 문의 예정
B52: 향후 충진·소분·세정 계획, 투자 예산 범위, 기존 연락사무소 현황은? | C52: 문의 예정
